{
"meta":{"test_sets":[],"test_metrics":[],"learn_metrics":[{"best_value":"Min","name":"RMSE"}],"launch_mode":"Train","parameters":"","iteration_count":1000,"learn_sets":["learn"],"name":"experiment"},
"iterations":[
{"learn":[14.64183031],"iteration":0,"passed_time":0.001710563248,"remaining_time":1.708852685},
{"learn":[14.24733384],"iteration":1,"passed_time":0.003744046645,"remaining_time":1.868279276},
{"learn":[13.81067577],"iteration":2,"passed_time":0.006552111267,"remaining_time":2.177484978},
{"learn":[13.44720295],"iteration":3,"passed_time":0.009282255771,"remaining_time":2.311281687},
{"learn":[13.04048787],"iteration":4,"passed_time":0.0121122871,"remaining_time":2.410345133},
{"learn":[12.67047099],"iteration":5,"passed_time":0.01478609279,"remaining_time":2.449562705},
{"learn":[12.29383181],"iteration":6,"passed_time":0.01781025253,"remaining_time":2.526511537},
{"learn":[11.93151076],"iteration":7,"passed_time":0.02051314984,"remaining_time":2.54363058},
{"learn":[11.59778313],"iteration":8,"passed_time":0.0230999475,"remaining_time":2.543560885},
{"learn":[11.3003589],"iteration":9,"passed_time":0.02528627006,"remaining_time":2.503340735},
{"learn":[10.99699863],"iteration":10,"passed_time":0.02766209817,"remaining_time":2.487074099},
{"learn":[10.70884352],"iteration":11,"passed_time":0.03013568283,"remaining_time":2.48117122},
{"learn":[10.40672993],"iteration":12,"passed_time":0.03165263155,"remaining_time":2.40316518},
{"learn":[10.12135451],"iteration":13,"passed_time":0.03416727578,"remaining_time":2.406352423},
{"learn":[9.865270518],"iteration":14,"passed_time":0.03626053198,"remaining_time":2.381108267},
{"learn":[9.604782715],"iteration":15,"passed_time":0.03840210198,"remaining_time":2.361729272},
{"learn":[9.365254804],"iteration":16,"passed_time":0.04036104389,"remaining_time":2.333818008},
{"learn":[9.129347317],"iteration":17,"passed_time":0.0431665986,"remaining_time":2.354977768},
{"learn":[8.91388195],"iteration":18,"passed_time":0.04552666333,"remaining_time":2.350613512},
{"learn":[8.694541209],"iteration":19,"passed_time":0.04774550738,"remaining_time":2.339529861},
{"learn":[8.500644501],"iteration":20,"passed_time":0.05014542175,"remaining_time":2.337731804},
{"learn":[8.285918165],"iteration":21,"passed_time":0.05248240444,"remaining_time":2.333081434},
{"learn":[8.087307012],"iteration":22,"passed_time":0.05415155286,"remaining_time":2.300263789},
{"learn":[7.890544413],"iteration":23,"passed_time":0.05673348684,"remaining_time":2.307161798},
{"learn":[7.719210061],"iteration":24,"passed_time":0.05865295874,"remaining_time":2.287465391},
{"learn":[7.556252402],"iteration":25,"passed_time":0.06045492773,"remaining_time":2.2647346},
{"learn":[7.375440582],"iteration":26,"passed_time":0.06265140024,"remaining_time":2.257770831},
{"learn":[7.211735676],"iteration":27,"passed_time":0.0647163216,"remaining_time":2.246580878},
{"learn":[7.056736673],"iteration":28,"passed_time":0.06619668116,"remaining_time":2.216447497},
{"learn":[6.907513768],"iteration":29,"passed_time":0.06809315736,"remaining_time":2.201678755},
{"learn":[6.764584717],"iteration":30,"passed_time":0.07022551221,"remaining_time":2.195113591},
{"learn":[6.618838116],"iteration":31,"passed_time":0.07280930838,"remaining_time":2.202481579},
{"learn":[6.474555946],"iteration":32,"passed_time":0.07512346721,"remaining_time":2.201345236},
{"learn":[6.34630552],"iteration":33,"passed_time":0.07746936762,"remaining_time":2.201041445},
{"learn":[6.225472264],"iteration":34,"passed_time":0.07916767417,"remaining_time":2.182765874},
{"learn":[6.11060184],"iteration":35,"passed_time":0.08137915536,"remaining_time":2.179152938},
{"learn":[5.995164864],"iteration":36,"passed_time":0.08343879788,"remaining_time":2.171663848},
{"learn":[5.872999326],"iteration":37,"passed_time":0.08573390763,"remaining_time":2.170421556},
{"learn":[5.760308012],"iteration":38,"passed_time":0.08817745924,"remaining_time":2.172783034},
{"learn":[5.665524504],"iteration":39,"passed_time":0.08996185264,"remaining_time":2.159084463},
{"learn":[5.566124054],"iteration":40,"passed_time":0.09192189956,"remaining_time":2.150075651},
{"learn":[5.490993946],"iteration":41,"passed_time":0.09398959644,"remaining_time":2.143857938},
{"learn":[5.405877335],"iteration":42,"passed_time":0.09642019117,"remaining_time":2.145909836},
{"learn":[5.322467886],"iteration":43,"passed_time":0.09892609779,"remaining_time":2.149394307},
{"learn":[5.241668891],"iteration":44,"passed_time":0.1013099712,"remaining_time":2.150022722},
{"learn":[5.171157862],"iteration":45,"passed_time":0.1037457547,"remaining_time":2.151596739},
{"learn":[5.10271099],"iteration":46,"passed_time":0.1058072978,"remaining_time":2.145411805},
{"learn":[5.035048246],"iteration":47,"passed_time":0.1080879896,"remaining_time":2.143745127},
{"learn":[4.971617592],"iteration":48,"passed_time":0.1102965982,"remaining_time":2.140654386},
{"learn":[4.89922183],"iteration":49,"passed_time":0.1126344372,"remaining_time":2.140054307},
{"learn":[4.840842721],"iteration":50,"passed_time":0.1148581032,"remaining_time":2.137261568},
{"learn":[4.777562044],"iteration":51,"passed_time":0.1170371662,"remaining_time":2.133677568},
{"learn":[4.720385969],"iteration":52,"passed_time":0.1190890299,"remaining_time":2.127873798},
{"learn":[4.668185707],"iteration":53,"passed_time":0.120922405,"remaining_time":2.118381392},
{"learn":[4.61088841],"iteration":54,"passed_time":0.1231176953,"remaining_time":2.115385855},
{"learn":[4.554398559],"iteration":55,"passed_time":0.1253484362,"remaining_time":2.113016496},
{"learn":[4.511052163],"iteration":56,"passed_time":0.1272555866,"remaining_time":2.105298564},
{"learn":[4.466272223],"iteration":57,"passed_time":0.1296416022,"remaining_time":2.105558436},
{"learn":[4.420523505],"iteration":58,"passed_time":0.131995866,"remaining_time":2.105222202},
{"learn":[4.377026286],"iteration":59,"passed_time":0.1338614061,"remaining_time":2.097162029},
{"learn":[4.335902338],"iteration":60,"passed_time":0.1363404159,"remaining_time":2.098748369},
{"learn":[4.291974701],"iteration":61,"passed_time":0.1384289926,"remaining_time":2.094296695},
{"learn":[4.250247684],"iteration":62,"passed_time":0.1405245572,"remaining_time":2.090023969},
{"learn":[4.209456251],"iteration":63,"passed_time":0.1426140638,"remaining_time":2.085730683},
{"learn":[4.172376098],"iteration":64,"passed_time":0.1448596044,"remaining_time":2.083749694},
{"learn":[4.140788343],"iteration":65,"passed_time":0.1472024091,"remaining_time":2.083137123},
{"learn":[4.105539658],"iteration":66,"passed_time":0.1492684231,"remaining_time":2.078618488},
{"learn":[4.074167181],"iteration":67,"passed_time":0.1514665475,"remaining_time":2.075982681},
{"learn":[4.042007101],"iteration":68,"passed_time":0.1536084079,"remaining_time":2.072600402},
{"learn":[4.010670108],"iteration":69,"passed_time":0.1556848007,"remaining_time":2.06838378},
{"learn":[3.982276677],"iteration":70,"passed_time":0.1578457329,"remaining_time":2.065333603},
{"learn":[3.955263642],"iteration":71,"passed_time":0.1604371546,"remaining_time":2.06785666},
{"learn":[3.928207705],"iteration":72,"passed_time":0.1629984,"remaining_time":2.069856394},
{"learn":[3.90378685],"iteration":73,"passed_time":0.1653593483,"remaining_time":2.06922644},
{"learn":[3.879826939],"iteration":74,"passed_time":0.16781568,"remaining_time":2.06972672},
{"learn":[3.854983523],"iteration":75,"passed_time":0.1698902998,"remaining_time":2.065508382},
{"learn":[3.831624382],"iteration":76,"passed_time":0.1720853835,"remaining_time":2.062789727},
{"learn":[3.810962434],"iteration":77,"passed_time":0.1742855639,"remaining_time":2.060144742},
{"learn":[3.793775503],"iteration":78,"passed_time":0.1763867761,"remaining_time":2.056357226},
{"learn":[3.776248051],"iteration":79,"passed_time":0.1782564261,"remaining_time":2.0499489},
{"learn":[3.758473686],"iteration":80,"passed_time":0.1806559509,"remaining_time":2.049664431},
{"learn":[3.737749925],"iteration":81,"passed_time":0.1828137168,"remaining_time":2.046621854},
{"learn":[3.720922674],"iteration":82,"passed_time":0.1848736542,"remaining_time":2.04251977},
{"learn":[3.701382753],"iteration":83,"passed_time":0.187111421,"remaining_time":2.040405495},
{"learn":[3.681244439],"iteration":84,"passed_time":0.1889232541,"remaining_time":2.033703264},
{"learn":[3.665265135],"iteration":85,"passed_time":0.1908876103,"remaining_time":2.028735765},
{"learn":[3.648686527],"iteration":86,"passed_time":0.1926448114,"remaining_time":2.021663366},
{"learn":[3.631928558],"iteration":87,"passed_time":0.1942172744,"remaining_time":2.012797208},
{"learn":[3.620175044],"iteration":88,"passed_time":0.1960651208,"remaining_time":2.006913765},
{"learn":[3.607169419],"iteration":89,"passed_time":0.198098023,"remaining_time":2.002991122},
{"learn":[3.591235184],"iteration":90,"passed_time":0.1999382191,"remaining_time":1.997185067},
{"learn":[3.576754885],"iteration":91,"passed_time":0.2015023398,"remaining_time":1.988740484},
{"learn":[3.564940974],"iteration":92,"passed_time":0.2035840767,"remaining_time":1.985492016},
{"learn":[3.553762614],"iteration":93,"passed_time":0.2050026959,"remaining_time":1.975877048},
{"learn":[3.543104566],"iteration":94,"passed_time":0.2067467109,"remaining_time":1.969534456},
{"learn":[3.534425511],"iteration":95,"passed_time":0.2080918544,"remaining_time":1.959531629},
{"learn":[3.524638941],"iteration":96,"passed_time":0.2102204056,"remaining_time":1.95700027},
{"learn":[3.51331071],"iteration":97,"passed_time":0.2122435023,"remaining_time":1.953506521},
{"learn":[3.501523224],"iteration":98,"passed_time":0.2141398678,"remaining_time":1.9488891},
{"learn":[3.489772376],"iteration":99,"passed_time":0.2164206897,"remaining_time":1.947786207},
{"learn":[3.476773289],"iteration":100,"passed_time":0.2187894152,"remaining_time":1.947442418},
{"learn":[3.466355234],"iteration":101,"passed_time":0.2212813141,"remaining_time":1.948143334},
{"learn":[3.456002146],"iteration":102,"passed_time":0.2233632492,"remaining_time":1.945211986},
{"learn":[3.445503948],"iteration":103,"passed_time":0.2252157321,"remaining_time":1.940320153},
{"learn":[3.436665857],"iteration":104,"passed_time":0.227008878,"remaining_time":1.934980436},
{"learn":[3.427358461],"iteration":105,"passed_time":0.2287750964,"remaining_time":1.92948053},
{"learn":[3.419428247],"iteration":106,"passed_time":0.2304982707,"remaining_time":1.923691175},
{"learn":[3.412593809],"iteration":107,"passed_time":0.2322051137,"remaining_time":1.917842236},
{"learn":[3.406821319],"iteration":108,"passed_time":0.2338234277,"remaining_time":1.911345634},
{"learn":[3.39800878],"iteration":109,"passed_time":0.2356824097,"remaining_time":1.906884951},
{"learn":[3.390839295],"iteration":110,"passed_time":0.2372641605,"remaining_time":1.900250799},
{"learn":[3.38325789],"iteration":111,"passed_time":0.2388899506,"remaining_time":1.894056037},
{"learn":[3.377314313],"iteration":112,"passed_time":0.2406871521,"remaining_time":1.889287645},
{"learn":[3.371303711],"iteration":113,"passed_time":0.2426245297,"remaining_time":1.885660818},
{"learn":[3.366365123],"iteration":114,"passed_time":0.2439779324,"remaining_time":1.877569306},
{"learn":[3.360233396],"iteration":115,"passed_time":0.2454084122,"remaining_time":1.870181348},
{"learn":[3.353302107],"iteration":116,"passed_time":0.2466812825,"remaining_time":1.861705747},
{"learn":[3.34579315],"iteration":117,"passed_time":0.2478895485,"remaining_time":1.852869337},
{"learn":[3.340189215],"iteration":118,"passed_time":0.2493316496,"remaining_time":1.845892297},
{"learn":[3.334043797],"iteration":119,"passed_time":0.2508547124,"remaining_time":1.839601225},
{"learn":[3.326300346],"iteration":120,"passed_time":0.2526077427,"remaining_time":1.835059552},
{"learn":[3.320152364],"iteration":121,"passed_time":0.2543708257,"remaining_time":1.830635943},
{"learn":[3.315906561],"iteration":122,"passed_time":0.2559647383,"remaining_time":1.825049394},
{"learn":[3.310277271],"iteration":123,"passed_time":0.2575606175,"remaining_time":1.819541137},
{"learn":[3.304697017],"iteration":124,"passed_time":0.2588217475,"remaining_time":1.811752232},
{"learn":[3.301337619],"iteration":125,"passed_time":0.2597482012,"remaining_time":1.801745459},
{"learn":[3.297099437],"iteration":126,"passed_time":0.2610531122,"remaining_time":1.794483204},
{"learn":[3.292784688],"iteration":127,"passed_time":0.2624822283,"remaining_time":1.788160181},
{"learn":[3.286479996],"iteration":128,"passed_time":0.2641765094,"remaining_time":1.783703408},
{"learn":[3.282200485],"iteration":129,"passed_time":0.265987829,"remaining_time":1.780072394},
{"learn":[3.276902377],"iteration":130,"passed_time":0.2676709067,"remaining_time":1.775618457},
{"learn":[3.272801097],"iteration":131,"passed_time":0.2692543264,"remaining_time":1.770551177},
{"learn":[3.268743362],"iteration":132,"passed_time":0.2708805783,"remaining_time":1.765815499},
{"learn":[3.26392876],"iteration":133,"passed_time":0.2722216347,"remaining_time":1.759283102},
{"learn":[3.258808215],"iteration":134,"passed_time":0.2737525945,"remaining_time":1.754044402},
{"learn":[3.251411124],"iteration":135,"passed_time":0.2753904442,"remaining_time":1.749539292},
{"learn":[3.248009652],"iteration":136,"passed_time":0.277170881,"remaining_time":1.745974236},
{"learn":[3.244720756],"iteration":137,"passed_time":0.2784259692,"remaining_time":1.739153517},
{"learn":[3.240722439],"iteration":138,"passed_time":0.280115769,"remaining_time":1.735105591},
{"learn":[3.237157551],"iteration":139,"passed_time":0.2818669474,"remaining_time":1.731468391},
{"learn":[3.233413754],"iteration":140,"passed_time":0.2833456537,"remaining_time":1.72619799},
{"learn":[3.230378292],"iteration":141,"passed_time":0.2852904004,"remaining_time":1.723796926},
{"learn":[3.224586019],"iteration":142,"passed_time":0.2870644145,"remaining_time":1.720379044},
{"learn":[3.220743987],"iteration":143,"passed_time":0.2888195498,"remaining_time":1.716871768},
{"learn":[3.216831086],"iteration":144,"passed_time":0.2906043633,"remaining_time":1.71356366},
{"learn":[3.213473334],"iteration":145,"passed_time":0.2941500495,"remaining_time":1.720576317},
{"learn":[3.211633891],"iteration":146,"passed_time":0.2952940483,"remaining_time":1.713509001},
{"learn":[3.20964227],"iteration":147,"passed_time":0.2966647049,"remaining_time":1.707826544},
{"learn":[3.207053934],"iteration":148,"passed_time":0.298575302,"remaining_time":1.705285785},
{"learn":[3.201703311],"iteration":149,"passed_time":0.3008055634,"remaining_time":1.704564859},
{"learn":[3.196003293],"iteration":150,"passed_time":0.3026792653,"remaining_time":1.70181918},
{"learn":[3.192129157],"iteration":151,"passed_time":0.3043699962,"remaining_time":1.698064189},
{"learn":[3.190128745],"iteration":152,"passed_time":0.3062708549,"remaining_time":1.695499438},
{"learn":[3.188171712],"iteration":153,"passed_time":0.3078675041,"remaining_time":1.691272133},
{"learn":[3.184853775],"iteration":154,"passed_time":0.3096508024,"remaining_time":1.68809631},
{"learn":[3.182460185],"iteration":155,"passed_time":0.31153654,"remaining_time":1.685492563},
{"learn":[3.177176628],"iteration":156,"passed_time":0.3133193595,"remaining_time":1.682345351},
{"learn":[3.174434899],"iteration":157,"passed_time":0.3149436976,"remaining_time":1.678370844},
{"learn":[3.171303464],"iteration":158,"passed_time":0.3163878773,"remaining_time":1.673472986},
{"learn":[3.167858156],"iteration":159,"passed_time":0.3178108216,"remaining_time":1.668506813},
{"learn":[3.164097283],"iteration":160,"passed_time":0.3197146619,"remaining_time":1.666090691},
{"learn":[3.160925474],"iteration":161,"passed_time":0.3215098558,"remaining_time":1.663118884},
{"learn":[3.159783583],"iteration":162,"passed_time":0.3232387659,"remaining_time":1.659821148},
{"learn":[3.157369178],"iteration":163,"passed_time":0.32517303,"remaining_time":1.657589348},
{"learn":[3.1549967],"iteration":164,"passed_time":0.3268714258,"remaining_time":1.654167518},
{"learn":[3.151267421],"iteration":165,"passed_time":0.3284284167,"remaining_time":1.650056021},
{"learn":[3.14774133],"iteration":166,"passed_time":0.3299655496,"remaining_time":1.645876065},
{"learn":[3.144284599],"iteration":167,"passed_time":0.3316423794,"remaining_time":1.642419403},
{"learn":[3.139452204],"iteration":168,"passed_time":0.3334135565,"remaining_time":1.639447725},
{"learn":[3.135764685],"iteration":169,"passed_time":0.3351817024,"remaining_time":1.63647537},
{"learn":[3.134006482],"iteration":170,"passed_time":0.3370691361,"remaining_time":1.634095402},
{"learn":[3.131371227],"iteration":171,"passed_time":0.3390664897,"remaining_time":1.632250311},
{"learn":[3.127659207],"iteration":172,"passed_time":0.3409318997,"remaining_time":1.629772723},
{"learn":[3.125519756],"iteration":173,"passed_time":0.3429110126,"remaining_time":1.627841934},
{"learn":[3.123270791],"iteration":174,"passed_time":0.3445740292,"remaining_time":1.624420423},
{"learn":[3.121077147],"iteration":175,"passed_time":0.3466888204,"remaining_time":1.623134023},
{"learn":[3.119568841],"iteration":176,"passed_time":0.3485131903,"remaining_time":1.620487885},
{"learn":[3.116833755],"iteration":177,"passed_time":0.3503528175,"remaining_time":1.617921438},
{"learn":[3.113526726],"iteration":178,"passed_time":0.3520312901,"remaining_time":1.614623962},
{"learn":[3.110025827],"iteration":179,"passed_time":0.3538093943,"remaining_time":1.611798352},
{"learn":[3.105774254],"iteration":180,"passed_time":0.3556788224,"remaining_time":1.609397544},
{"learn":[3.103836551],"iteration":181,"passed_time":0.3573638168,"remaining_time":1.606173638},
{"learn":[3.101688863],"iteration":182,"passed_time":0.3590714653,"remaining_time":1.603067689},
{"learn":[3.099543941],"iteration":183,"passed_time":0.3608909892,"remaining_time":1.600473083},
{"learn":[3.097674234],"iteration":184,"passed_time":0.3635065638,"remaining_time":1.601393781},
{"learn":[3.096036532],"iteration":185,"passed_time":0.3650648604,"remaining_time":1.597649443},
{"learn":[3.093292226],"iteration":186,"passed_time":0.3668320512,"remaining_time":1.594836672},
{"learn":[3.090614637],"iteration":187,"passed_time":0.3683963657,"remaining_time":1.591158771},
{"learn":[3.088955718],"iteration":188,"passed_time":0.3704578704,"remaining_time":1.589636682},
{"learn":[3.086444984],"iteration":189,"passed_time":0.372318401,"remaining_time":1.587252131},
{"learn":[3.086187381],"iteration":190,"passed_time":0.3733889972,"remaining_time":1.581527219},
{"learn":[3.084638666],"iteration":191,"passed_time":0.3748986174,"remaining_time":1.577698348},
{"learn":[3.082229065],"iteration":192,"passed_time":0.3766086374,"remaining_time":1.574731453},
{"learn":[3.080301651],"iteration":193,"passed_time":0.3781471038,"remaining_time":1.571064771},
{"learn":[3.078031901],"iteration":194,"passed_time":0.379975222,"remaining_time":1.56861566},
{"learn":[3.075550303],"iteration":195,"passed_time":0.3817139045,"remaining_time":1.565806016},
{"learn":[3.073990835],"iteration":196,"passed_time":0.3835454092,"remaining_time":1.563385602},
{"learn":[3.072272038],"iteration":197,"passed_time":0.3851551669,"remaining_time":1.560072949},
{"learn":[3.070164912],"iteration":198,"passed_time":0.3867380265,"remaining_time":1.556669142},
{"learn":[3.067720295],"iteration":199,"passed_time":0.3885450256,"remaining_time":1.554180102},
{"learn":[3.066151732],"iteration":200,"passed_time":0.3902965617,"remaining_time":1.551477377},
{"learn":[3.062516491],"iteration":201,"passed_time":0.3923915727,"remaining_time":1.550140965},
{"learn":[3.05983906],"iteration":202,"passed_time":0.3941935016,"remaining_time":1.547646408},
{"learn":[3.05747715],"iteration":203,"passed_time":0.395680578,"remaining_time":1.543930098},
{"learn":[3.053449795],"iteration":204,"passed_time":0.3974888453,"remaining_time":1.541481132},
{"learn":[3.050957762],"iteration":205,"passed_time":0.3993106185,"remaining_time":1.539090442},
{"learn":[3.048158992],"iteration":206,"passed_time":0.4007334561,"remaining_time":1.53517696},
{"learn":[3.046054551],"iteration":207,"passed_time":0.4022483097,"remaining_time":1.531637795},
{"learn":[3.043531123],"iteration":208,"passed_time":0.403995246,"remaining_time":1.528996362},
{"learn":[3.040846971],"iteration":209,"passed_time":0.4056042106,"remaining_time":1.525844411},
{"learn":[3.038300316],"iteration":210,"passed_time":0.4071568624,"remaining_time":1.522496514},
{"learn":[3.037320287],"iteration":211,"passed_time":0.4090131308,"remaining_time":1.52029409},
{"learn":[3.033903478],"iteration":212,"passed_time":0.4099679095,"remaining_time":1.51476406},
{"learn":[3.031546689],"iteration":213,"passed_time":0.412417277,"remaining_time":1.51476626},
{"learn":[3.029662598],"iteration":214,"passed_time":0.4132457648,"remaining_time":1.50882756},
{"learn":[3.027320839],"iteration":215,"passed_time":0.414048716,"remaining_time":1.502843488},
{"learn":[3.024505726],"iteration":216,"passed_time":0.4156375727,"remaining_time":1.499742947},
{"learn":[3.021825815],"iteration":217,"passed_time":0.4172983917,"remaining_time":1.496914414},
{"learn":[3.020627374],"iteration":218,"passed_time":0.4190487571,"remaining_time":1.494415887},
{"learn":[3.019281119],"iteration":219,"passed_time":0.4209353386,"remaining_time":1.49240711},
{"learn":[3.016661183],"iteration":220,"passed_time":0.4224589124,"remaining_time":1.489119877},
{"learn":[3.014035186],"iteration":221,"passed_time":0.4247045881,"remaining_time":1.488379142},
{"learn":[3.011473269],"iteration":222,"passed_time":0.4262480049,"remaining_time":1.485178026},
{"learn":[3.009665927],"iteration":223,"passed_time":0.4280224396,"remaining_time":1.482792023},
{"learn":[3.00616606],"iteration":224,"passed_time":0.4299426001,"remaining_time":1.4809134},
{"learn":[3.005475226],"iteration":225,"passed_time":0.4314142493,"remaining_time":1.477498358},
{"learn":[3.004082681],"iteration":226,"passed_time":0.4331598287,"remaining_time":1.475033249},
{"learn":[3.001112704],"iteration":227,"passed_time":0.4349763433,"remaining_time":1.472814636},
{"learn":[2.999219266],"iteration":228,"passed_time":0.436806315,"remaining_time":1.470644842},
{"learn":[2.997795597],"iteration":229,"passed_time":0.438710606,"remaining_time":1.468726811},
{"learn":[2.995693091],"iteration":230,"passed_time":0.440481717,"remaining_time":1.466365543},
{"learn":[2.992896165],"iteration":231,"passed_time":0.4421645328,"remaining_time":1.463717074},
{"learn":[2.990607149],"iteration":232,"passed_time":0.4438615571,"remaining_time":1.461123667},
{"learn":[2.990027758],"iteration":233,"passed_time":0.4456092152,"remaining_time":1.45870367},
{"learn":[2.98882229],"iteration":234,"passed_time":0.4473588436,"remaining_time":1.45629581},
{"learn":[2.985172691],"iteration":235,"passed_time":0.4491146407,"remaining_time":1.453913498},
{"learn":[2.98137997],"iteration":236,"passed_time":0.4510179241,"remaining_time":1.452011292},
{"learn":[2.97925777],"iteration":237,"passed_time":0.4532574278,"remaining_time":1.451185546},
{"learn":[2.976233228],"iteration":238,"passed_time":0.4551335905,"remaining_time":1.449191056},
{"learn":[2.973277297],"iteration":239,"passed_time":0.4568365059,"remaining_time":1.446648935},
{"learn":[2.971921023],"iteration":240,"passed_time":0.4587246893,"remaining_time":1.444697258},
{"learn":[2.971352754],"iteration":241,"passed_time":0.4600771874,"remaining_time":1.441068215},
{"learn":[2.970639824],"iteration":242,"passed_time":0.4618799128,"remaining_time":1.438860469},
{"learn":[2.968217438],"iteration":243,"passed_time":0.4636955992,"remaining_time":1.436696201},
{"learn":[2.966040812],"iteration":244,"passed_time":0.4653121728,"remaining_time":1.433921186},
{"learn":[2.964865874],"iteration":245,"passed_time":0.4669446362,"remaining_time":1.431204292},
{"learn":[2.962497194],"iteration":246,"passed_time":0.4688677156,"remaining_time":1.429382145},
{"learn":[2.960581294],"iteration":247,"passed_time":0.4709076048,"remaining_time":1.427913382},
{"learn":[2.960152618],"iteration":248,"passed_time":0.4722516647,"remaining_time":1.424341366},
{"learn":[2.958388901],"iteration":249,"passed_time":0.4739703749,"remaining_time":1.421911125},
{"learn":[2.956483492],"iteration":250,"passed_time":0.4757860881,"remaining_time":1.419776016},
{"learn":[2.953757115],"iteration":251,"passed_time":0.4773897305,"remaining_time":1.417013962},
{"learn":[2.951912224],"iteration":252,"passed_time":0.4788969667,"remaining_time":1.413976419},
{"learn":[2.950081732],"iteration":253,"passed_time":0.4805202588,"remaining_time":1.411291784},
{"learn":[2.947755449],"iteration":254,"passed_time":0.4822690941,"remaining_time":1.408982255},
{"learn":[2.947161928],"iteration":255,"passed_time":0.4837749634,"remaining_time":1.405970987},
{"learn":[2.945103177],"iteration":256,"passed_time":0.4856047269,"remaining_time":1.403907829},
{"learn":[2.942350739],"iteration":257,"passed_time":0.4873712853,"remaining_time":1.401664704},
{"learn":[2.940595714],"iteration":258,"passed_time":0.488777702,"remaining_time":1.398394893},
{"learn":[2.938498251],"iteration":259,"passed_time":0.4905147024,"remaining_time":1.396080307},
{"learn":[2.936566903],"iteration":260,"passed_time":0.4923374351,"remaining_time":1.394012891},
{"learn":[2.93502496],"iteration":261,"passed_time":0.4941148622,"remaining_time":1.391819726},
{"learn":[2.934377046],"iteration":262,"passed_time":0.4958522893,"remaining_time":1.389517632},
{"learn":[2.933788002],"iteration":263,"passed_time":0.4974512915,"remaining_time":1.386833904},
{"learn":[2.931302624],"iteration":264,"passed_time":0.498960335,"remaining_time":1.383908854},
{"learn":[2.928428441],"iteration":265,"passed_time":0.5005774461,"remaining_time":1.381292652},
{"learn":[2.926422136],"iteration":266,"passed_time":0.5025492098,"remaining_time":1.379657568},
{"learn":[2.924431051],"iteration":267,"passed_time":0.504604555,"remaining_time":1.378248262},
{"learn":[2.923167135],"iteration":268,"passed_time":0.5060667478,"remaining_time":1.375222278},
{"learn":[2.921249007],"iteration":269,"passed_time":0.5076935734,"remaining_time":1.372652995},
{"learn":[2.920145277],"iteration":270,"passed_time":0.5092230849,"remaining_time":1.369828889},
{"learn":[2.91754175],"iteration":271,"passed_time":0.5109694533,"remaining_time":1.367594713},
{"learn":[2.914338948],"iteration":272,"passed_time":0.5127803045,"remaining_time":1.365535829},
{"learn":[2.913264206],"iteration":273,"passed_time":0.5145504708,"remaining_time":1.363370955},
{"learn":[2.910547833],"iteration":274,"passed_time":0.5160658332,"remaining_time":1.360537197},
{"learn":[2.908727139],"iteration":275,"passed_time":0.5178189163,"remaining_time":1.358336578},
{"learn":[2.906935011],"iteration":276,"passed_time":0.5195867387,"remaining_time":1.356177661},
{"learn":[2.905522445],"iteration":277,"passed_time":0.5211863436,"remaining_time":1.353584677},
{"learn":[2.902854018],"iteration":278,"passed_time":0.5229879834,"remaining_time":1.351520918},
{"learn":[2.899917541],"iteration":279,"passed_time":0.5244025168,"remaining_time":1.348463615},
{"learn":[2.897227794],"iteration":280,"passed_time":0.5260380403,"remaining_time":1.345983456},
{"learn":[2.895378995],"iteration":281,"passed_time":0.5278809144,"remaining_time":1.344037222},
{"learn":[2.894560611],"iteration":282,"passed_time":0.5296998691,"remaining_time":1.342031117},
{"learn":[2.893672695],"iteration":283,"passed_time":0.5314690787,"remaining_time":1.339900917},
{"learn":[2.891477533],"iteration":284,"passed_time":0.5330161546,"remaining_time":1.337215967},
{"learn":[2.890771763],"iteration":285,"passed_time":0.5348533293,"remaining_time":1.335263207},
{"learn":[2.890387907],"iteration":286,"passed_time":0.536626892,"remaining_time":1.33315322},
{"learn":[2.888141045],"iteration":287,"passed_time":0.5385493204,"remaining_time":1.331413598},
{"learn":[2.884253553],"iteration":288,"passed_time":0.5402023146,"remaining_time":1.329009847},
{"learn":[2.882197748],"iteration":289,"passed_time":0.5418727614,"remaining_time":1.326654002},
{"learn":[2.880840677],"iteration":290,"passed_time":0.5434737534,"remaining_time":1.324133647},
{"learn":[2.878413392],"iteration":291,"passed_time":0.5450855154,"remaining_time":1.321645702},
{"learn":[2.874848463],"iteration":292,"passed_time":0.5466457569,"remaining_time":1.31903942},
{"learn":[2.873361758],"iteration":293,"passed_time":0.5484197781,"remaining_time":1.316953617},
{"learn":[2.870864686],"iteration":294,"passed_time":0.5502226972,"remaining_time":1.314938988},
{"learn":[2.869110422],"iteration":295,"passed_time":0.5523056568,"remaining_time":1.313591832},
{"learn":[2.866845072],"iteration":296,"passed_time":0.5542006934,"remaining_time":1.311794907},
{"learn":[2.865200992],"iteration":297,"passed_time":0.5556218097,"remaining_time":1.308880907},
{"learn":[2.862741932],"iteration":298,"passed_time":0.5573599989,"remaining_time":1.306720265},
{"learn":[2.860943523],"iteration":299,"passed_time":0.5591261806,"remaining_time":1.304627755},
{"learn":[2.860443471],"iteration":300,"passed_time":0.5605507681,"remaining_time":1.301744142},
{"learn":[2.859444024],"iteration":301,"passed_time":0.5619416506,"remaining_time":1.298792292},
{"learn":[2.85629944],"iteration":302,"passed_time":0.5636477699,"remaining_time":1.296575893},
{"learn":[2.854696561],"iteration":303,"passed_time":0.5653231518,"remaining_time":1.294292479},
{"learn":[2.85089487],"iteration":304,"passed_time":0.5670386989,"remaining_time":1.292104576},
{"learn":[2.848920794],"iteration":305,"passed_time":0.5688425743,"remaining_time":1.290120087},
{"learn":[2.847783194],"iteration":306,"passed_time":0.5704091735,"remaining_time":1.287601164},
{"learn":[2.845717724],"iteration":307,"passed_time":0.5721694617,"remaining_time":1.285523596},
{"learn":[2.844441346],"iteration":308,"passed_time":0.5735702075,"remaining_time":1.282644056},
{"learn":[2.843376426],"iteration":309,"passed_time":0.5750978018,"remaining_time":1.280056398},
{"learn":[2.840095381],"iteration":310,"passed_time":0.576802372,"remaining_time":1.277867635},
{"learn":[2.834660571],"iteration":311,"passed_time":0.5781120744,"remaining_time":1.274811241},
{"learn":[2.833407709],"iteration":312,"passed_time":0.5794045803,"remaining_time":1.271728264},
{"learn":[2.82963699],"iteration":313,"passed_time":0.5808799998,"remaining_time":1.269056305},
{"learn":[2.828471709],"iteration":314,"passed_time":0.5822911615,"remaining_time":1.266252208},
{"learn":[2.825569746],"iteration":315,"passed_time":0.5836445651,"remaining_time":1.263331907},
{"learn":[2.824626933],"iteration":316,"passed_time":0.5851925999,"remaining_time":1.260840838},
{"learn":[2.822663783],"iteration":317,"passed_time":0.5868056965,"remaining_time":1.258495236},
{"learn":[2.821971883],"iteration":318,"passed_time":0.5883170442,"remaining_time":1.255937013},
{"learn":[2.820115731],"iteration":319,"passed_time":0.5898341206,"remaining_time":1.253397506},
{"learn":[2.816545072],"iteration":320,"passed_time":0.5912524296,"remaining_time":1.250655451},
{"learn":[2.814821786],"iteration":321,"passed_time":0.5922671005,"remaining_time":1.247071721},
{"learn":[2.813562658],"iteration":322,"passed_time":0.5930429482,"remaining_time":1.243003331},
{"learn":[2.810569069],"iteration":323,"passed_time":0.5942020061,"remaining_time":1.239754803},
{"learn":[2.809175733],"iteration":324,"passed_time":0.595333253,"remaining_time":1.236461372},
{"learn":[2.808683355],"iteration":325,"passed_time":0.5966843631,"remaining_time":1.233635769},
{"learn":[2.805509815],"iteration":326,"passed_time":0.5979323416,"remaining_time":1.230606929},
{"learn":[2.801509911],"iteration":327,"passed_time":0.5990192332,"remaining_time":1.227258917},
{"learn":[2.79914863],"iteration":328,"passed_time":0.6007804657,"remaining_time":1.225299977},
{"learn":[2.797477963],"iteration":329,"passed_time":0.602293714,"remaining_time":1.222838753},
{"learn":[2.796970343],"iteration":330,"passed_time":0.603812603,"remaining_time":1.220394657},
{"learn":[2.796359331],"iteration":331,"passed_time":0.6057340329,"remaining_time":1.218766066},
{"learn":[2.793388606],"iteration":332,"passed_time":0.6072424142,"remaining_time":1.216308379},
{"learn":[2.79152304],"iteration":333,"passed_time":0.6092643642,"remaining_time":1.214880439},
{"learn":[2.790304355],"iteration":334,"passed_time":0.6113767815,"remaining_time":1.213628536},
{"learn":[2.787832672],"iteration":335,"passed_time":0.6130369663,"remaining_time":1.211477814},
{"learn":[2.785857182],"iteration":336,"passed_time":0.6147737771,"remaining_time":1.209480754},
{"learn":[2.783806854],"iteration":337,"passed_time":0.6164570382,"remaining_time":1.207380353},
{"learn":[2.780828791],"iteration":338,"passed_time":0.6182164498,"remaining_time":1.205430895},
{"learn":[2.778775495],"iteration":339,"passed_time":0.6198876673,"remaining_time":1.203311354},
{"learn":[2.775615913],"iteration":340,"passed_time":0.6215177159,"remaining_time":1.201114882},
{"learn":[2.773027489],"iteration":341,"passed_time":0.6234663116,"remaining_time":1.1995346},
{"learn":[2.770886813],"iteration":342,"passed_time":0.6251418839,"remaining_time":1.197429206},
{"learn":[2.768733699],"iteration":343,"passed_time":0.6267063331,"remaining_time":1.195114403},
{"learn":[2.76594637],"iteration":344,"passed_time":0.6281443703,"remaining_time":1.192563949},
{"learn":[2.765536237],"iteration":345,"passed_time":0.6295972955,"remaining_time":1.190048067},
{"learn":[2.762269603],"iteration":346,"passed_time":0.6314156847,"remaining_time":1.188226058},
{"learn":[2.760349744],"iteration":347,"passed_time":0.632965663,"remaining_time":1.185901185},
{"learn":[2.75689531],"iteration":348,"passed_time":0.6347021416,"remaining_time":1.183928637},
{"learn":[2.753950093],"iteration":349,"passed_time":0.6361646038,"remaining_time":1.18144855},
{"learn":[2.751956863],"iteration":350,"passed_time":0.63798271,"remaining_time":1.179631848},
{"learn":[2.750530517],"iteration":351,"passed_time":0.6394636178,"remaining_time":1.177194387},
{"learn":[2.74826552],"iteration":352,"passed_time":0.6411116744,"remaining_time":1.175068706},
{"learn":[2.746514017],"iteration":353,"passed_time":0.642947464,"remaining_time":1.17328831},
{"learn":[2.744590849],"iteration":354,"passed_time":0.6446455913,"remaining_time":1.171257483},
{"learn":[2.742609502],"iteration":355,"passed_time":0.646339432,"remaining_time":1.16922077},
{"learn":[2.741259624],"iteration":356,"passed_time":0.6479388564,"remaining_time":1.167015923},
{"learn":[2.737935394],"iteration":357,"passed_time":0.6497076392,"remaining_time":1.165118169},
{"learn":[2.736779747],"iteration":358,"passed_time":0.6512062684,"remaining_time":1.162738769},
{"learn":[2.734202098],"iteration":359,"passed_time":0.6529864759,"remaining_time":1.160864846},
{"learn":[2.731599731],"iteration":360,"passed_time":0.6545390245,"remaining_time":1.158588467},
{"learn":[2.730040519],"iteration":361,"passed_time":0.6561500086,"remaining_time":1.156419076},
{"learn":[2.728875929],"iteration":362,"passed_time":0.6574688303,"remaining_time":1.153740069},
{"learn":[2.728490388],"iteration":363,"passed_time":0.6591817721,"remaining_time":1.151757162},
{"learn":[2.724896341],"iteration":364,"passed_time":0.6607793099,"remaining_time":1.149574964},
{"learn":[2.72292652],"iteration":365,"passed_time":0.662507585,"remaining_time":1.147622429},
{"learn":[2.721186789],"iteration":366,"passed_time":0.6639471044,"remaining_time":1.145173071},
{"learn":[2.720414804],"iteration":367,"passed_time":0.6654532443,"remaining_time":1.142843615},
{"learn":[2.718651517],"iteration":368,"passed_time":0.6673084969,"remaining_time":1.141115614},
{"learn":[2.716113669],"iteration":369,"passed_time":0.6688554658,"remaining_time":1.138862009},
{"learn":[2.715021252],"iteration":370,"passed_time":0.6706929091,"remaining_time":1.137104689},
{"learn":[2.713733673],"iteration":371,"passed_time":0.6721587135,"remaining_time":1.134719549},
{"learn":[2.712492984],"iteration":372,"passed_time":0.6738010737,"remaining_time":1.132636121},
{"learn":[2.708612998],"iteration":373,"passed_time":0.6755491035,"remaining_time":1.130731922},
{"learn":[2.705979846],"iteration":374,"passed_time":0.6773377678,"remaining_time":1.12889628},
{"learn":[2.705107154],"iteration":375,"passed_time":0.6790112974,"remaining_time":1.126869813},
{"learn":[2.704443976],"iteration":376,"passed_time":0.6807279446,"remaining_time":1.124916471},
{"learn":[2.702081925],"iteration":377,"passed_time":0.6822086594,"remaining_time":1.122576154},
{"learn":[2.700160909],"iteration":378,"passed_time":0.6837674629,"remaining_time":1.120368323},
{"learn":[2.69718625],"iteration":379,"passed_time":0.6851955918,"remaining_time":1.117950702},
{"learn":[2.695612893],"iteration":380,"passed_time":0.6866395725,"remaining_time":1.11556403},
{"learn":[2.690837009],"iteration":381,"passed_time":0.6880055037,"remaining_time":1.113056024},
{"learn":[2.689591441],"iteration":382,"passed_time":0.6890020467,"remaining_time":1.109958911},
{"learn":[2.686493526],"iteration":383,"passed_time":0.6899794361,"remaining_time":1.106842012},
{"learn":[2.68355967],"iteration":384,"passed_time":0.6906216995,"remaining_time":1.103200897},
{"learn":[2.681895172],"iteration":385,"passed_time":0.6917933818,"remaining_time":1.100417452},
{"learn":[2.680247934],"iteration":386,"passed_time":0.6931540639,"remaining_time":1.097941708},
{"learn":[2.678041114],"iteration":387,"passed_time":0.6946992579,"remaining_time":1.095762747},
{"learn":[2.677272021],"iteration":388,"passed_time":0.6961086826,"remaining_time":1.093373792},
{"learn":[2.675896355],"iteration":389,"passed_time":0.6975375765,"remaining_time":1.091020312},
{"learn":[2.673801762],"iteration":390,"passed_time":0.6992501044,"remaining_time":1.089113334},
{"learn":[2.66955271],"iteration":391,"passed_time":0.7008447725,"remaining_time":1.087024545},
{"learn":[2.668579776],"iteration":392,"passed_time":0.7025041023,"remaining_time":1.085038143},
{"learn":[2.666224439],"iteration":393,"passed_time":0.703968206,"remaining_time":1.082753129},
{"learn":[2.662430266],"iteration":394,"passed_time":0.7055083136,"remaining_time":1.080588683},
{"learn":[2.661257732],"iteration":395,"passed_time":0.7071917119,"remaining_time":1.078645944},
{"learn":[2.658677025],"iteration":396,"passed_time":0.7083307888,"remaining_time":1.075877747},
{"learn":[2.657079087],"iteration":397,"passed_time":0.7097054102,"remaining_time":1.073474012},
{"learn":[2.655730204],"iteration":398,"passed_time":0.7110627732,"remaining_time":1.07104944},
{"learn":[2.65391238],"iteration":399,"passed_time":0.7125728448,"remaining_time":1.068859267},
{"learn":[2.652191241],"iteration":400,"passed_time":0.7143494805,"remaining_time":1.06707067},
{"learn":[2.651404193],"iteration":401,"passed_time":0.7158296108,"remaining_time":1.064841063},
{"learn":[2.650114479],"iteration":402,"passed_time":0.7174509473,"remaining_time":1.062824356},
{"learn":[2.648303849],"iteration":403,"passed_time":0.7188522528,"remaining_time":1.060485007},
{"learn":[2.646772657],"iteration":404,"passed_time":0.7203992247,"remaining_time":1.058364293},
{"learn":[2.645072483],"iteration":405,"passed_time":0.7218843033,"remaining_time":1.056155853},
{"learn":[2.644396236],"iteration":406,"passed_time":0.7230960339,"remaining_time":1.053552698},
{"learn":[2.642545016],"iteration":407,"passed_time":0.7250024861,"remaining_time":1.051964392},
{"learn":[2.642076783],"iteration":408,"passed_time":0.7270502285,"remaining_time":1.050578692},
{"learn":[2.64083863],"iteration":409,"passed_time":0.72890489,"remaining_time":1.048911915},
{"learn":[2.638502535],"iteration":410,"passed_time":0.7305501901,"remaining_time":1.04694419},
{"learn":[2.636343716],"iteration":411,"passed_time":0.7324304919,"remaining_time":1.04531342},
{"learn":[2.634179869],"iteration":412,"passed_time":0.7342026339,"remaining_time":1.043527715},
{"learn":[2.630597234],"iteration":413,"passed_time":0.7360120942,"remaining_time":1.041794897},
{"learn":[2.629989329],"iteration":414,"passed_time":0.7377433494,"remaining_time":1.039951468},
{"learn":[2.629118505],"iteration":415,"passed_time":0.7397882311,"remaining_time":1.038548863},
{"learn":[2.623863947],"iteration":416,"passed_time":0.7420002621,"remaining_time":1.037376865},
{"learn":[2.623689364],"iteration":417,"passed_time":0.7438453334,"remaining_time":1.035688957},
{"learn":[2.621078018],"iteration":418,"passed_time":0.7458253882,"remaining_time":1.034187471},
{"learn":[2.618210899],"iteration":419,"passed_time":0.7477608841,"remaining_time":1.032622173},
{"learn":[2.614426947],"iteration":420,"passed_time":0.749269277,"remaining_time":1.030467723},
{"learn":[2.610618588],"iteration":421,"passed_time":0.751243171,"remaining_time":1.028953917},
{"learn":[2.609069685],"iteration":422,"passed_time":0.7528432835,"remaining_time":1.026928072},
{"learn":[2.607533383],"iteration":423,"passed_time":0.7547926327,"remaining_time":1.025378671},
{"learn":[2.607167411],"iteration":424,"passed_time":0.7564551974,"remaining_time":1.023439385},
{"learn":[2.604389632],"iteration":425,"passed_time":0.7584935581,"remaining_time":1.022007752},
{"learn":[2.602592856],"iteration":426,"passed_time":0.7608409997,"remaining_time":1.020988039},
{"learn":[2.600686163],"iteration":427,"passed_time":0.7630628729,"remaining_time":1.019794307},
{"learn":[2.599990078],"iteration":428,"passed_time":0.7652598618,"remaining_time":1.01856266},
{"learn":[2.598672791],"iteration":429,"passed_time":0.7671827557,"remaining_time":1.016963188},
{"learn":[2.596405389],"iteration":430,"passed_time":0.7688111102,"remaining_time":1.014973368},
{"learn":[2.594745071],"iteration":431,"passed_time":0.7707998885,"remaining_time":1.013459113},
{"learn":[2.592057116],"iteration":432,"passed_time":0.7728175709,"remaining_time":1.011980514},
{"learn":[2.591878279],"iteration":433,"passed_time":0.7744955999,"remaining_time":1.010056474},
{"learn":[2.590625075],"iteration":434,"passed_time":0.7761851023,"remaining_time":1.008148466},
{"learn":[2.588081469],"iteration":435,"passed_time":0.7777819366,"remaining_time":1.006121588},
{"learn":[2.586208481],"iteration":436,"passed_time":0.7791389353,"remaining_time":1.00378769},
{"learn":[2.583791045],"iteration":437,"passed_time":0.7808943127,"remaining_time":1.001969415},
{"learn":[2.582219482],"iteration":438,"passed_time":0.782508545,"remaining_time":0.9999710563},
{"learn":[2.580900924],"iteration":439,"passed_time":0.7839131353,"remaining_time":0.9977076268},
{"learn":[2.580518382],"iteration":440,"passed_time":0.7853901283,"remaining_time":0.9955398678},
{"learn":[2.579212697],"iteration":441,"passed_time":0.7869538194,"remaining_time":0.993484686},
{"learn":[2.577147335],"iteration":442,"passed_time":0.7884668165,"remaining_time":0.9913679837},
{"learn":[2.57654255],"iteration":443,"passed_time":0.790488686,"remaining_time":0.9898912374},
{"learn":[2.574629757],"iteration":444,"passed_time":0.7920415071,"remaining_time":0.9878270482},
{"learn":[2.574273616],"iteration":445,"passed_time":0.7936144167,"remaining_time":0.985790105},
{"learn":[2.57228415],"iteration":446,"passed_time":0.7952711638,"remaining_time":0.9838589566},
{"learn":[2.569496757],"iteration":447,"passed_time":0.796738277,"remaining_time":0.981695377},
{"learn":[2.567534101],"iteration":448,"passed_time":0.7982313034,"remaining_time":0.9795666997},
{"learn":[2.564779054],"iteration":449,"passed_time":0.7997440135,"remaining_time":0.9774649053},
{"learn":[2.562471408],"iteration":450,"passed_time":0.8015098675,"remaining_time":0.9756738742},
{"learn":[2.561500885],"iteration":451,"passed_time":0.8034168332,"remaining_time":0.9740540367},
{"learn":[2.559903593],"iteration":452,"passed_time":0.8048459853,"remaining_time":0.971855969},
{"learn":[2.55764509],"iteration":453,"passed_time":0.8067146897,"remaining_time":0.9701899132},
{"learn":[2.556775663],"iteration":454,"passed_time":0.8084366215,"remaining_time":0.968347162},
{"learn":[2.554600942],"iteration":455,"passed_time":0.8102745398,"remaining_time":0.9666433106},
{"learn":[2.552913371],"iteration":456,"passed_time":0.8119713183,"remaining_time":0.9647711726},
{"learn":[2.550757615],"iteration":457,"passed_time":0.8138444485,"remaining_time":0.9631084959},
{"learn":[2.547945789],"iteration":458,"passed_time":0.8154195388,"remaining_time":0.9610936176},
{"learn":[2.54674186],"iteration":459,"passed_time":0.8170795477,"remaining_time":0.9591803385},
{"learn":[2.54607573],"iteration":460,"passed_time":0.8189462308,"remaining_time":0.9575098013},
{"learn":[2.542978915],"iteration":461,"passed_time":0.8211293598,"remaining_time":0.9562069168},
{"learn":[2.541961177],"iteration":462,"passed_time":0.82356499,"remaining_time":0.9551930878},
{"learn":[2.540392068],"iteration":463,"passed_time":0.8255479674,"remaining_time":0.9536502382},
{"learn":[2.539454866],"iteration":464,"passed_time":0.8273173686,"remaining_time":0.9518597682},
{"learn":[2.535843987],"iteration":465,"passed_time":0.8289948907,"remaining_time":0.9499641023},
{"learn":[2.533315668],"iteration":466,"passed_time":0.8303729577,"remaining_time":0.9477275941},
{"learn":[2.532273178],"iteration":467,"passed_time":0.8322887386,"remaining_time":0.946106002},
{"learn":[2.530592639],"iteration":468,"passed_time":0.8340750169,"remaining_time":0.944336533},
{"learn":[2.529949365],"iteration":469,"passed_time":0.8358660243,"remaining_time":0.9425723252},
{"learn":[2.528801605],"iteration":470,"passed_time":0.8375274401,"remaining_time":0.940662454},
{"learn":[2.527643662],"iteration":471,"passed_time":0.8391130604,"remaining_time":0.9386688472},
{"learn":[2.525067753],"iteration":472,"passed_time":0.840809753,"remaining_time":0.9368007184},
{"learn":[2.522802496],"iteration":473,"passed_time":0.8427383909,"remaining_time":0.9351907038},
{"learn":[2.5215449],"iteration":474,"passed_time":0.8443530507,"remaining_time":0.9332323192},
{"learn":[2.519812124],"iteration":475,"passed_time":0.845985947,"remaining_time":0.9312954543},
{"learn":[2.519394562],"iteration":476,"passed_time":0.8481372816,"remaining_time":0.9299282982},
{"learn":[2.517280544],"iteration":477,"passed_time":0.8495837218,"remaining_time":0.9277880811},
{"learn":[2.515200745],"iteration":478,"passed_time":0.8514723072,"remaining_time":0.9261316744},
{"learn":[2.51395215],"iteration":479,"passed_time":0.8533253155,"remaining_time":0.9244357585},
{"learn":[2.511532478],"iteration":480,"passed_time":0.8553350324,"remaining_time":0.9229082782},
{"learn":[2.509480421],"iteration":481,"passed_time":0.8570135777,"remaining_time":0.9210228905},
{"learn":[2.507405821],"iteration":482,"passed_time":0.8588001142,"remaining_time":0.9192539524},
{"learn":[2.504297073],"iteration":483,"passed_time":0.861143427,"remaining_time":0.9180785296},
{"learn":[2.502430443],"iteration":484,"passed_time":0.8627290981,"remaining_time":0.9160937845},
{"learn":[2.501552674],"iteration":485,"passed_time":0.8644270692,"remaining_time":0.9142294518},
{"learn":[2.500986434],"iteration":486,"passed_time":0.8658675903,"remaining_time":0.9120946074},
{"learn":[2.498502828],"iteration":487,"passed_time":0.8677336782,"remaining_time":0.9104091049},
{"learn":[2.497918169],"iteration":488,"passed_time":0.8697169591,"remaining_time":0.9088453295},
{"learn":[2.497093664],"iteration":489,"passed_time":0.8711238723,"remaining_time":0.9066799487},
{"learn":[2.496717423],"iteration":490,"passed_time":0.872888813,"remaining_time":0.9048888103},
{"learn":[2.495591967],"iteration":491,"passed_time":0.8745088137,"remaining_time":0.9029481247},
{"learn":[2.491266052],"iteration":492,"passed_time":0.8762488895,"remaining_time":0.9011322251},
{"learn":[2.490509166],"iteration":493,"passed_time":0.8780076678,"remaining_time":0.8993357893},
{"learn":[2.490316455],"iteration":494,"passed_time":0.879640705,"remaining_time":0.8974112243},
{"learn":[2.488667508],"iteration":495,"passed_time":0.8811656845,"remaining_time":0.8953780343},
{"learn":[2.486305975],"iteration":496,"passed_time":0.8829478886,"remaining_time":0.8936072192},
{"learn":[2.485759691],"iteration":497,"passed_time":0.8848807469,"remaining_time":0.8919882228},
{"learn":[2.482941432],"iteration":498,"passed_time":0.8864453473,"remaining_time":0.8899982344},
{"learn":[2.481105398],"iteration":499,"passed_time":0.8883325117,"remaining_time":0.8883325117},
{"learn":[2.480371169],"iteration":500,"passed_time":0.8899178258,"remaining_time":0.8863652596},
{"learn":[2.477781748],"iteration":501,"passed_time":0.8917052153,"remaining_time":0.8845999945},
{"learn":[2.476449227],"iteration":502,"passed_time":0.8932685941,"remaining_time":0.8826133028},
{"learn":[2.475281259],"iteration":503,"passed_time":0.8950326282,"remaining_time":0.880825761},
{"learn":[2.472946245],"iteration":504,"passed_time":0.8970126453,"remaining_time":0.8792500187},
{"learn":[2.471939585],"iteration":505,"passed_time":0.8987671688,"remaining_time":0.8774525324},
{"learn":[2.470800628],"iteration":506,"passed_time":0.9004458112,"remaining_time":0.8755814299},
{"learn":[2.469101334],"iteration":507,"passed_time":0.9025573977,"remaining_time":0.8741303931},
{"learn":[2.467525723],"iteration":508,"passed_time":0.9041741428,"remaining_time":0.8721994187},
{"learn":[2.465593235],"iteration":509,"passed_time":0.9059111403,"remaining_time":0.8703852132},
{"learn":[2.465348888],"iteration":510,"passed_time":0.9076343444,"remaining_time":0.8685581104},
{"learn":[2.461756652],"iteration":511,"passed_time":0.9092351836,"remaining_time":0.8666147844},
{"learn":[2.460287614],"iteration":512,"passed_time":0.9110161252,"remaining_time":0.864843768},
{"learn":[2.459251845],"iteration":513,"passed_time":0.9124091376,"remaining_time":0.8627059161},
{"learn":[2.457963938],"iteration":514,"passed_time":0.9143851351,"remaining_time":0.8611199816},
{"learn":[2.456680547],"iteration":515,"passed_time":0.9161301944,"remaining_time":0.8593159187},
{"learn":[2.455238411],"iteration":516,"passed_time":0.9181530722,"remaining_time":0.8577716322},
{"learn":[2.453994358],"iteration":517,"passed_time":0.9200393327,"remaining_time":0.8560983753},
{"learn":[2.452039646],"iteration":518,"passed_time":0.9218672712,"remaining_time":0.8543702456},
{"learn":[2.449624259],"iteration":519,"passed_time":0.9237132728,"remaining_time":0.8526584057},
{"learn":[2.446949879],"iteration":520,"passed_time":0.9257064162,"remaining_time":0.8510813308},
{"learn":[2.445192881],"iteration":521,"passed_time":0.927668812,"remaining_time":0.849474506},
{"learn":[2.444865169],"iteration":522,"passed_time":0.9294307599,"remaining_time":0.8476835037},
{"learn":[2.443861584],"iteration":523,"passed_time":0.9312292862,"remaining_time":0.8459258401},
{"learn":[2.441415002],"iteration":524,"passed_time":0.9329994847,"remaining_time":0.8441423909},
{"learn":[2.440032251],"iteration":525,"passed_time":0.9345783853,"remaining_time":0.8421866057},
{"learn":[2.438088466],"iteration":526,"passed_time":0.9364962023,"remaining_time":0.8405364397},
{"learn":[2.437233435],"iteration":527,"passed_time":0.9383601418,"remaining_time":0.8388370964},
{"learn":[2.43618731],"iteration":528,"passed_time":0.9402757096,"remaining_time":0.8371830987},
{"learn":[2.435109918],"iteration":529,"passed_time":0.9420456197,"remaining_time":0.8353989458},
{"learn":[2.433259179],"iteration":530,"passed_time":0.9436545558,"remaining_time":0.833472668},
{"learn":[2.431889267],"iteration":531,"passed_time":0.9452493028,"remaining_time":0.831535101},
{"learn":[2.429529702],"iteration":532,"passed_time":0.947222395,"remaining_time":0.8299303161},
{"learn":[2.428075308],"iteration":533,"passed_time":0.9486448923,"remaining_time":0.82784367},
{"learn":[2.426438663],"iteration":534,"passed_time":0.9506329647,"remaining_time":0.8262510814},
{"learn":[2.42619204],"iteration":535,"passed_time":0.9520867859,"remaining_time":0.8241945311},
{"learn":[2.423121509],"iteration":536,"passed_time":0.9537628349,"remaining_time":0.8223318297},
{"learn":[2.422174037],"iteration":537,"passed_time":0.9557508474,"remaining_time":0.8207377165},
{"learn":[2.421233832],"iteration":538,"passed_time":0.957716901,"remaining_time":0.8191233606},
{"learn":[2.419467557],"iteration":539,"passed_time":0.9595745024,"remaining_time":0.8174153169},
{"learn":[2.417804595],"iteration":540,"passed_time":0.96152447,"remaining_time":0.8157850864},
{"learn":[2.415106301],"iteration":541,"passed_time":0.9630550436,"remaining_time":0.8137992804},
{"learn":[2.412741846],"iteration":542,"passed_time":0.964720611,"remaining_time":0.8119287647},
{"learn":[2.410859776],"iteration":543,"passed_time":0.9665418129,"remaining_time":0.8101894608},
{"learn":[2.410444958],"iteration":544,"passed_time":0.9682567837,"remaining_time":0.8083611681},
{"learn":[2.409373839],"iteration":545,"passed_time":0.970272837,"remaining_time":0.806783641},
{"learn":[2.407876545],"iteration":546,"passed_time":0.9721468904,"remaining_time":0.8050869129},
{"learn":[2.406420922],"iteration":547,"passed_time":0.9737130026,"remaining_time":0.8031355423},
{"learn":[2.405173489],"iteration":548,"passed_time":0.975284763,"remaining_time":0.8011902151},
{"learn":[2.403222669],"iteration":549,"passed_time":0.9770889383,"remaining_time":0.799436404},
{"learn":[2.402253692],"iteration":550,"passed_time":0.978736626,"remaining_time":0.7975548912},
{"learn":[2.401752194],"iteration":551,"passed_time":0.9809689458,"remaining_time":0.7961487096},
{"learn":[2.401061566],"iteration":552,"passed_time":0.9826652844,"remaining_time":0.7943062968},
{"learn":[2.39877364],"iteration":553,"passed_time":0.9842622091,"remaining_time":0.7923843777},
{"learn":[2.398007555],"iteration":554,"passed_time":0.9862172271,"remaining_time":0.7907507497},
{"learn":[2.395452545],"iteration":555,"passed_time":0.9881884865,"remaining_time":0.7891289352},
{"learn":[2.393090071],"iteration":556,"passed_time":0.9896463126,"remaining_time":0.7870975161},
{"learn":[2.392086939],"iteration":557,"passed_time":0.9911608361,"remaining_time":0.7851130637},
{"learn":[2.39149146],"iteration":558,"passed_time":0.9925702166,"remaining_time":0.7830473444},
{"learn":[2.389966472],"iteration":559,"passed_time":0.9941975322,"remaining_time":0.7811552038},
{"learn":[2.388988132],"iteration":560,"passed_time":0.9961867496,"remaining_time":0.7795472069},
{"learn":[2.386841247],"iteration":561,"passed_time":0.9980399389,"remaining_time":0.7778318385},
{"learn":[2.384497375],"iteration":562,"passed_time":0.9998053563,"remaining_time":0.776047852},
{"learn":[2.382954304],"iteration":563,"passed_time":1.001624104,"remaining_time":0.7743051584},
{"learn":[2.380034771],"iteration":564,"passed_time":1.003234809,"remaining_time":0.7724020211},
{"learn":[2.379788769],"iteration":565,"passed_time":1.004788388,"remaining_time":0.7704561136},
{"learn":[2.378971056],"iteration":566,"passed_time":1.006830409,"remaining_time":0.7688845979},
{"learn":[2.377002785],"iteration":567,"passed_time":1.00866296,"remaining_time":0.7671521103},
{"learn":[2.375945607],"iteration":568,"passed_time":1.010411696,"remaining_time":0.7653557835},
{"learn":[2.372574596],"iteration":569,"passed_time":1.012355981,"remaining_time":0.7637071434},
{"learn":[2.371604781],"iteration":570,"passed_time":1.013796797,"remaining_time":0.7616792049},
{"learn":[2.370467122],"iteration":571,"passed_time":1.015887483,"remaining_time":0.760139585},
{"learn":[2.366393289],"iteration":572,"passed_time":1.017833649,"remaining_time":0.7584903456},
{"learn":[2.365958444],"iteration":573,"passed_time":1.019568354,"remaining_time":0.7566831341},
{"learn":[2.364394385],"iteration":574,"passed_time":1.021057212,"remaining_time":0.7546944611},
{"learn":[2.362153344],"iteration":575,"passed_time":1.022862989,"remaining_time":0.7529408112},
{"learn":[2.359502981],"iteration":576,"passed_time":1.024627642,"remaining_time":0.7511568326},
{"learn":[2.358505797],"iteration":577,"passed_time":1.026214915,"remaining_time":0.7492434158},
{"learn":[2.355153154],"iteration":578,"passed_time":1.028293629,"remaining_time":0.7476884588},
{"learn":[2.354600428],"iteration":579,"passed_time":1.029962523,"remaining_time":0.7458349307},
{"learn":[2.352446966],"iteration":580,"passed_time":1.031954119,"remaining_time":0.7442147602},
{"learn":[2.349507559],"iteration":581,"passed_time":1.034254365,"remaining_time":0.7428149904},
{"learn":[2.34796775],"iteration":582,"passed_time":1.036069282,"remaining_time":0.7410649926},
{"learn":[2.347537698],"iteration":583,"passed_time":1.038092607,"remaining_time":0.7394632272},
{"learn":[2.346261875],"iteration":584,"passed_time":1.039997881,"remaining_time":0.7377762749},
{"learn":[2.344589642],"iteration":585,"passed_time":1.041707877,"remaining_time":0.735950616},
{"learn":[2.343819085],"iteration":586,"passed_time":1.043549668,"remaining_time":0.73421808},
{"learn":[2.342198588],"iteration":587,"passed_time":1.045208177,"remaining_time":0.7323567502},
{"learn":[2.33973891],"iteration":588,"passed_time":1.047060979,"remaining_time":0.7306316847},
{"learn":[2.338289482],"iteration":589,"passed_time":1.049027669,"remaining_time":0.728985329},
{"learn":[2.337341869],"iteration":590,"passed_time":1.050876003,"remaining_time":0.7272559817},
{"learn":[2.337196981],"iteration":591,"passed_time":1.05256867,"remaining_time":0.7254189479},
{"learn":[2.333813546],"iteration":592,"passed_time":1.054277192,"remaining_time":0.7235932834},
{"learn":[2.331465869],"iteration":593,"passed_time":1.056038856,"remaining_time":0.7218043358},
{"learn":[2.329541386],"iteration":594,"passed_time":1.058324893,"remaining_time":0.7203724059},
{"learn":[2.328936488],"iteration":595,"passed_time":1.060089008,"remaining_time":0.7185838239},
{"learn":[2.328684847],"iteration":596,"passed_time":1.061743914,"remaining_time":0.7167216033},
{"learn":[2.327736216],"iteration":597,"passed_time":1.063288314,"remaining_time":0.7147857899},
{"learn":[2.326886276],"iteration":598,"passed_time":1.064826055,"remaining_time":0.7128468245},
{"learn":[2.325710948],"iteration":599,"passed_time":1.066355783,"remaining_time":0.7109038553},
{"learn":[2.324552709],"iteration":600,"passed_time":1.06807714,"remaining_time":0.7090894821},
{"learn":[2.324276378],"iteration":601,"passed_time":1.069644062,"remaining_time":0.707173317},
{"learn":[2.322161569],"iteration":602,"passed_time":1.071350247,"remaining_time":0.7053499965},
{"learn":[2.321369028],"iteration":603,"passed_time":1.073089093,"remaining_time":0.7035484785},
{"learn":[2.320175514],"iteration":604,"passed_time":1.074830611,"remaining_time":0.7017489115},
{"learn":[2.317947051],"iteration":605,"passed_time":1.076488865,"remaining_time":0.6998954004},
{"learn":[2.316938064],"iteration":606,"passed_time":1.078006917,"remaining_time":0.6979517601},
{"learn":[2.315670473],"iteration":607,"passed_time":1.079501451,"remaining_time":0.6959943565},
{"learn":[2.313586849],"iteration":608,"passed_time":1.08146569,"remaining_time":0.6943400406},
{"learn":[2.311832488],"iteration":609,"passed_time":1.083397395,"remaining_time":0.6926639085},
{"learn":[2.309304089],"iteration":610,"passed_time":1.085028908,"remaining_time":0.6907958188},
{"learn":[2.308090408],"iteration":611,"passed_time":1.08683752,"remaining_time":0.6890407809},
{"learn":[2.307278076],"iteration":612,"passed_time":1.088683684,"remaining_time":0.6873092749},
{"learn":[2.306233383],"iteration":613,"passed_time":1.090375153,"remaining_time":0.6854801453},
{"learn":[2.305042438],"iteration":614,"passed_time":1.09215475,"remaining_time":0.6837066322},
{"learn":[2.304325665],"iteration":615,"passed_time":1.093579543,"remaining_time":0.6817119229},
{"learn":[2.302830363],"iteration":616,"passed_time":1.095336045,"remaining_time":0.679924968},
{"learn":[2.301176987],"iteration":617,"passed_time":1.096888156,"remaining_time":0.6780117727},
{"learn":[2.300741393],"iteration":618,"passed_time":1.098239372,"remaining_time":0.6759760919},
{"learn":[2.297103307],"iteration":619,"passed_time":1.099962706,"remaining_time":0.674170691},
{"learn":[2.294864066],"iteration":620,"passed_time":1.101478293,"remaining_time":0.6722387648},
{"learn":[2.29231806],"iteration":621,"passed_time":1.103126624,"remaining_time":0.6703888489},
{"learn":[2.291070943],"iteration":622,"passed_time":1.104672177,"remaining_time":0.668477385},
{"learn":[2.289603726],"iteration":623,"passed_time":1.106198665,"remaining_time":0.6665556058},
{"learn":[2.288341261],"iteration":624,"passed_time":1.10811961,"remaining_time":0.6648717657},
{"learn":[2.286290307],"iteration":625,"passed_time":1.109689041,"remaining_time":0.6629771586},
{"learn":[2.285329098],"iteration":626,"passed_time":1.111215465,"remaining_time":0.6610580039},
{"learn":[2.284305211],"iteration":627,"passed_time":1.112663763,"remaining_time":0.6590938213},
{"learn":[2.283330702],"iteration":628,"passed_time":1.114547679,"remaining_time":0.6573882178},
{"learn":[2.281265915],"iteration":629,"passed_time":1.116150894,"remaining_time":0.6555171917},
{"learn":[2.280601307],"iteration":630,"passed_time":1.117686358,"remaining_time":0.6536073946},
{"learn":[2.280560269],"iteration":631,"passed_time":1.119358366,"remaining_time":0.6517782893},
{"learn":[2.279776918],"iteration":632,"passed_time":1.121214246,"remaining_time":0.6500562846},
{"learn":[2.278685497],"iteration":633,"passed_time":1.122676228,"remaining_time":0.6481064661},
{"learn":[2.276502449],"iteration":634,"passed_time":1.124307811,"remaining_time":0.6462556708},
{"learn":[2.275728906],"iteration":635,"passed_time":1.126048421,"remaining_time":0.6444679641},
{"learn":[2.274880754],"iteration":636,"passed_time":1.127659099,"remaining_time":0.6426063627},
{"learn":[2.27291641],"iteration":637,"passed_time":1.129179784,"remaining_time":0.6406944858},
{"learn":[2.272573183],"iteration":638,"passed_time":1.130721362,"remaining_time":0.6387956363},
{"learn":[2.271659282],"iteration":639,"passed_time":1.132852738,"remaining_time":0.6372296654},
{"learn":[2.269968166],"iteration":640,"passed_time":1.134910213,"remaining_time":0.6356205403},
{"learn":[2.269383893],"iteration":641,"passed_time":1.136691472,"remaining_time":0.6338559919},
{"learn":[2.267648037],"iteration":642,"passed_time":1.138481176,"remaining_time":0.6320960806},
{"learn":[2.26712808],"iteration":643,"passed_time":1.140417885,"remaining_time":0.63041734},
{"learn":[2.26593697],"iteration":644,"passed_time":1.141959533,"remaining_time":0.628520363},
{"learn":[2.26346125],"iteration":645,"passed_time":1.143494895,"remaining_time":0.6266210414},
{"learn":[2.261129374],"iteration":646,"passed_time":1.145404291,"remaining_time":0.624926916},
{"learn":[2.259802434],"iteration":647,"passed_time":1.147348555,"remaining_time":0.6232510671},
{"learn":[2.259399162],"iteration":648,"passed_time":1.149061744,"remaining_time":0.6214494176},
{"learn":[2.257995223],"iteration":649,"passed_time":1.15069685,"remaining_time":0.6196059964},
{"learn":[2.257063524],"iteration":650,"passed_time":1.152601581,"remaining_time":0.6179077602},
{"learn":[2.256143778],"iteration":651,"passed_time":1.153971826,"remaining_time":0.6159236127},
{"learn":[2.255156936],"iteration":652,"passed_time":1.155672467,"remaining_time":0.6141169158},
{"learn":[2.253183893],"iteration":653,"passed_time":1.157662982,"remaining_time":0.6124639015},
{"learn":[2.252601969],"iteration":654,"passed_time":1.159442614,"remaining_time":0.6106987812},
{"learn":[2.251467121],"iteration":655,"passed_time":1.161245542,"remaining_time":0.6089458331},
{"learn":[2.250207297],"iteration":656,"passed_time":1.163328311,"remaining_time":0.6073388288},
{"learn":[2.249994705],"iteration":657,"passed_time":1.165132666,"remaining_time":0.6055856716},
{"learn":[2.249786358],"iteration":658,"passed_time":1.167121237,"remaining_time":0.6039276813},
{"learn":[2.248890367],"iteration":659,"passed_time":1.168687768,"remaining_time":0.6020512742},
{"learn":[2.248754734],"iteration":660,"passed_time":1.170012544,"remaining_time":0.6000518188},
{"learn":[2.248067613],"iteration":661,"passed_time":1.171634503,"remaining_time":0.598206136},
{"learn":[2.246111646],"iteration":662,"passed_time":1.173692085,"remaining_time":0.5965825528},
{"learn":[2.245422827],"iteration":663,"passed_time":1.175399133,"remaining_time":0.5947802843},
{"learn":[2.244731946],"iteration":664,"passed_time":1.177079203,"remaining_time":0.5929647112},
{"learn":[2.24404131],"iteration":665,"passed_time":1.179531179,"remaining_time":0.5915366576},
{"learn":[2.243284505],"iteration":666,"passed_time":1.180519531,"remaining_time":0.5893748185},
{"learn":[2.242491627],"iteration":667,"passed_time":1.181715939,"remaining_time":0.587319898},
{"learn":[2.240888281],"iteration":668,"passed_time":1.183514839,"remaining_time":0.5855656379},
{"learn":[2.238762186],"iteration":669,"passed_time":1.185237608,"remaining_time":0.5837737471},
{"learn":[2.236305372],"iteration":670,"passed_time":1.186803407,"remaining_time":0.5819050981},
{"learn":[2.235527632],"iteration":671,"passed_time":1.188573957,"remaining_time":0.5801372887},
{"learn":[2.233684873],"iteration":672,"passed_time":1.190533229,"remaining_time":0.5784611677},
{"learn":[2.23267832],"iteration":673,"passed_time":1.192266532,"remaining_time":0.5766749102},
{"learn":[2.230915239],"iteration":674,"passed_time":1.194161654,"remaining_time":0.5749667222},
{"learn":[2.229329349],"iteration":675,"passed_time":1.196567751,"remaining_time":0.5735028867},
{"learn":[2.227908033],"iteration":676,"passed_time":1.198794445,"remaining_time":0.5719506731},
{"learn":[2.227614664],"iteration":677,"passed_time":1.200722941,"remaining_time":0.5702548479},
{"learn":[2.226646394],"iteration":678,"passed_time":1.202521105,"remaining_time":0.5684967229},
{"learn":[2.225562816],"iteration":679,"passed_time":1.204287672,"remaining_time":0.5667236102},
{"learn":[2.223390124],"iteration":680,"passed_time":1.20656876,"remaining_time":0.5651915339},
{"learn":[2.222110137],"iteration":681,"passed_time":1.20828612,"remaining_time":0.5633944078},
{"learn":[2.221657454],"iteration":682,"passed_time":1.210001784,"remaining_time":0.5615967284},
{"learn":[2.220189871],"iteration":683,"passed_time":1.211901853,"remaining_time":0.5598844816},
{"learn":[2.218508228],"iteration":684,"passed_time":1.213475089,"remaining_time":0.5580213915},
{"learn":[2.216514671],"iteration":685,"passed_time":1.215036344,"remaining_time":0.5561536617},
{"learn":[2.216304967],"iteration":686,"passed_time":1.216604607,"remaining_time":0.5542900176},
{"learn":[2.21584773],"iteration":687,"passed_time":1.218088346,"remaining_time":0.552388901},
{"learn":[2.215333132],"iteration":688,"passed_time":1.220731327,"remaining_time":0.5510122534},
{"learn":[2.214300036],"iteration":689,"passed_time":1.222260121,"remaining_time":0.5491313585},
{"learn":[2.212966557],"iteration":690,"passed_time":1.224082534,"remaining_time":0.5473827831},
{"learn":[2.211496176],"iteration":691,"passed_time":1.225770916,"remaining_time":0.5455743382},
{"learn":[2.210578799],"iteration":692,"passed_time":1.227546517,"remaining_time":0.5438048786},
{"learn":[2.208753703],"iteration":693,"passed_time":1.228931847,"remaining_time":0.5418633217},
{"learn":[2.207908709],"iteration":694,"passed_time":1.230518574,"remaining_time":0.5400117484},
{"learn":[2.205847976],"iteration":695,"passed_time":1.232424749,"remaining_time":0.538300465},
{"learn":[2.20417164],"iteration":696,"passed_time":1.233906805,"remaining_time":0.5364042493},
{"learn":[2.203812301],"iteration":697,"passed_time":1.235616536,"remaining_time":0.5346077275},
{"learn":[2.202246343],"iteration":698,"passed_time":1.237268789,"remaining_time":0.5327867033},
{"learn":[2.200948566],"iteration":699,"passed_time":1.238800379,"remaining_time":0.5309144482},
{"learn":[2.199552465],"iteration":700,"passed_time":1.240744413,"remaining_time":0.5292190862},
{"learn":[2.197732309],"iteration":701,"passed_time":1.242428175,"remaining_time":0.5274125301},
{"learn":[2.196038562],"iteration":702,"passed_time":1.244274369,"remaining_time":0.5256749466},
{"learn":[2.194863],"iteration":703,"passed_time":1.245755757,"remaining_time":0.5237836706},
{"learn":[2.194103533],"iteration":704,"passed_time":1.247476626,"remaining_time":0.5219937655},
{"learn":[2.192674899],"iteration":705,"passed_time":1.249095262,"remaining_time":0.520161483},
{"learn":[2.19244333],"iteration":706,"passed_time":1.25071055,"remaining_time":0.5183284173},
{"learn":[2.189982488],"iteration":707,"passed_time":1.252456373,"remaining_time":0.5165498034},
{"learn":[2.18924307],"iteration":708,"passed_time":1.254671364,"remaining_time":0.5149638461},
{"learn":[2.187841867],"iteration":709,"passed_time":1.256445178,"remaining_time":0.5131959178},
{"learn":[2.18630294],"iteration":710,"passed_time":1.258134227,"remaining_time":0.5113935184},
{"learn":[2.185619065],"iteration":711,"passed_time":1.259868434,"remaining_time":0.5096097038},
{"learn":[2.18488692],"iteration":712,"passed_time":1.261943733,"remaining_time":0.5079633259},
{"learn":[2.184232301],"iteration":713,"passed_time":1.264111711,"remaining_time":0.5063528701},
{"learn":[2.18215644],"iteration":714,"passed_time":1.266049876,"remaining_time":0.5046492515},
{"learn":[2.181100183],"iteration":715,"passed_time":1.267927501,"remaining_time":0.5029209641},
{"learn":[2.179919643],"iteration":716,"passed_time":1.269544085,"remaining_time":0.5010892274},
{"learn":[2.17853189],"iteration":717,"passed_time":1.271329245,"remaining_time":0.4993242996},
{"learn":[2.176969164],"iteration":718,"passed_time":1.272647047,"remaining_time":0.4973766624},
{"learn":[2.176573742],"iteration":719,"passed_time":1.274204293,"remaining_time":0.4955238919},
{"learn":[2.176083556],"iteration":720,"passed_time":1.27576749,"remaining_time":0.4936742439},
{"learn":[2.173056464],"iteration":721,"passed_time":1.277726231,"remaining_time":0.49197769},
{"learn":[2.171200522],"iteration":722,"passed_time":1.279238684,"remaining_time":0.4901094268},
{"learn":[2.170955969],"iteration":723,"passed_time":1.280636833,"remaining_time":0.4881985717},
{"learn":[2.170784323],"iteration":724,"passed_time":1.282239182,"remaining_time":0.4863665863},
{"learn":[2.168724524],"iteration":725,"passed_time":1.283863275,"remaining_time":0.4845434401},
{"learn":[2.166970516],"iteration":726,"passed_time":1.285520817,"remaining_time":0.4827334016},
{"learn":[2.165090944],"iteration":727,"passed_time":1.28701318,"remaining_time":0.4808620674},
{"learn":[2.164312318],"iteration":728,"passed_time":1.288748221,"remaining_time":0.4790819862},
{"learn":[2.162680028],"iteration":729,"passed_time":1.290529929,"remaining_time":0.477319289},
{"learn":[2.161573652],"iteration":730,"passed_time":1.292402513,"remaining_time":0.4755899809},
{"learn":[2.159913927],"iteration":731,"passed_time":1.293950215,"remaining_time":0.4737413357},
{"learn":[2.157125433],"iteration":732,"passed_time":1.295700111,"remaining_time":0.471967162},
{"learn":[2.156130192],"iteration":733,"passed_time":1.29751992,"remaining_time":0.4702183906},
{"learn":[2.154950089],"iteration":734,"passed_time":1.299195011,"remaining_time":0.4684172489},
{"learn":[2.154249465],"iteration":735,"passed_time":1.300882292,"remaining_time":0.4666208223},
{"learn":[2.154076507],"iteration":736,"passed_time":1.302830055,"remaining_time":0.464917645},
{"learn":[2.152419577],"iteration":737,"passed_time":1.304620064,"remaining_time":0.4631578004},
{"learn":[2.151911482],"iteration":738,"passed_time":1.306425789,"remaining_time":0.461403425},
{"learn":[2.150737147],"iteration":739,"passed_time":1.308154891,"remaining_time":0.4596219888},
{"learn":[2.149034192],"iteration":740,"passed_time":1.310283772,"remaining_time":0.4579804276},
{"learn":[2.148135724],"iteration":741,"passed_time":1.312184014,"remaining_time":0.4562580535},
{"learn":[2.146232212],"iteration":742,"passed_time":1.31410871,"remaining_time":0.4545436587},
{"learn":[2.143722226],"iteration":743,"passed_time":1.315819364,"remaining_time":0.4527550499},
{"learn":[2.143318889],"iteration":744,"passed_time":1.317752339,"remaining_time":0.4510427471},
{"learn":[2.142600752],"iteration":745,"passed_time":1.31951411,"remaining_time":0.4492715602},
{"learn":[2.140488211],"iteration":746,"passed_time":1.321063958,"remaining_time":0.4474286231},
{"learn":[2.138814681],"iteration":747,"passed_time":1.322775915,"remaining_time":0.4456410838},
{"learn":[2.137565127],"iteration":748,"passed_time":1.324363978,"remaining_time":0.4438122277},
{"learn":[2.136911339],"iteration":749,"passed_time":1.326172703,"remaining_time":0.4420575676},
{"learn":[2.136069423],"iteration":750,"passed_time":1.327942765,"remaining_time":0.4402899446},
{"learn":[2.135303905],"iteration":751,"passed_time":1.329562067,"remaining_time":0.4384725967},
{"learn":[2.135009521],"iteration":752,"passed_time":1.331394462,"remaining_time":0.4367256733},
{"learn":[2.134523009],"iteration":753,"passed_time":1.333109033,"remaining_time":0.4349400822},
{"learn":[2.133925428],"iteration":754,"passed_time":1.334654753,"remaining_time":0.4330998867},
{"learn":[2.132577416],"iteration":755,"passed_time":1.336298464,"remaining_time":0.4312920969},
{"learn":[2.131642359],"iteration":756,"passed_time":1.337870516,"remaining_time":0.4294617377},
{"learn":[2.131116711],"iteration":757,"passed_time":1.339409658,"remaining_time":0.4276215531},
{"learn":[2.128848026],"iteration":758,"passed_time":1.341127826,"remaining_time":0.4258390066},
{"learn":[2.127263725],"iteration":759,"passed_time":1.34279736,"remaining_time":0.4240412714},
{"learn":[2.126337383],"iteration":760,"passed_time":1.344641631,"remaining_time":0.4222987514},
{"learn":[2.126137008],"iteration":761,"passed_time":1.345973139,"remaining_time":0.4203958099},
{"learn":[2.124138724],"iteration":762,"passed_time":1.347658981,"remaining_time":0.4186044278},
{"learn":[2.123607337],"iteration":763,"passed_time":1.349372131,"remaining_time":0.4168217576},
{"learn":[2.122386313],"iteration":764,"passed_time":1.350903878,"remaining_time":0.4149835442},
{"learn":[2.1219634],"iteration":765,"passed_time":1.352688711,"remaining_time":0.4132234443},
{"learn":[2.121011588],"iteration":766,"passed_time":1.354598589,"remaining_time":0.4115012664},
{"learn":[2.118424945],"iteration":767,"passed_time":1.356574874,"remaining_time":0.4097986597},
{"learn":[2.11678182],"iteration":768,"passed_time":1.358281773,"remaining_time":0.4080144207},
{"learn":[2.115034589],"iteration":769,"passed_time":1.360091532,"remaining_time":0.4062611069},
{"learn":[2.114735948],"iteration":770,"passed_time":1.361617896,"remaining_time":0.4044234735},
{"learn":[2.112932349],"iteration":771,"passed_time":1.363051464,"remaining_time":0.4025592405},
{"learn":[2.112122861],"iteration":772,"passed_time":1.364813658,"remaining_time":0.4007926266},
{"learn":[2.111182491],"iteration":773,"passed_time":1.366351554,"remaining_time":0.3989605312},
{"learn":[2.108394648],"iteration":774,"passed_time":1.36828591,"remaining_time":0.3972442965},
{"learn":[2.107816641],"iteration":775,"passed_time":1.370136276,"remaining_time":0.3955032549},
{"learn":[2.107085403],"iteration":776,"passed_time":1.371709583,"remaining_time":0.3936824156},
{"learn":[2.106312184],"iteration":777,"passed_time":1.373806478,"remaining_time":0.3920116171},
{"learn":[2.105137074],"iteration":778,"passed_time":1.375677454,"remaining_time":0.390275632},
{"learn":[2.10295509],"iteration":779,"passed_time":1.377586474,"remaining_time":0.388550031},
{"learn":[2.10145666],"iteration":780,"passed_time":1.379103287,"remaining_time":0.3867139818},
{"learn":[2.100748151],"iteration":781,"passed_time":1.381035071,"remaining_time":0.3849944315},
{"learn":[2.100256627],"iteration":782,"passed_time":1.382575438,"remaining_time":0.3831658621},
{"learn":[2.098874199],"iteration":783,"passed_time":1.384236208,"remaining_time":0.3813712003},
{"learn":[2.098327949],"iteration":784,"passed_time":1.385761763,"remaining_time":0.3795398458},
{"learn":[2.098158057],"iteration":785,"passed_time":1.387134766,"remaining_time":0.3776677352},
{"learn":[2.095656017],"iteration":786,"passed_time":1.388686421,"remaining_time":0.3758452448},
{"learn":[2.094408097],"iteration":787,"passed_time":1.39045616,"remaining_time":0.3740821141},
{"learn":[2.093446477],"iteration":788,"passed_time":1.392361016,"remaining_time":0.3723551006},
{"learn":[2.092810209],"iteration":789,"passed_time":1.394281904,"remaining_time":0.3706318987},
{"learn":[2.091638972],"iteration":790,"passed_time":1.396164628,"remaining_time":0.3688981128},
{"learn":[2.089799644],"iteration":791,"passed_time":1.397903638,"remaining_time":0.3671262079},
{"learn":[2.087720799],"iteration":792,"passed_time":1.39961254,"remaining_time":0.3653465268},
{"learn":[2.086465605],"iteration":793,"passed_time":1.401276442,"remaining_time":0.363555349},
{"learn":[2.084879701],"iteration":794,"passed_time":1.402802946,"remaining_time":0.3617290615},
{"learn":[2.082810564],"iteration":795,"passed_time":1.4047455,"remaining_time":0.3600101534},
{"learn":[2.081082705],"iteration":796,"passed_time":1.406473969,"remaining_time":0.3582361553},
{"learn":[2.08076769],"iteration":797,"passed_time":1.407875149,"remaining_time":0.3563794236},
{"learn":[2.07922001],"iteration":798,"passed_time":1.409800273,"remaining_time":0.3546556381},
{"learn":[2.077368118],"iteration":799,"passed_time":1.411785482,"remaining_time":0.3529463706},
{"learn":[2.076903372],"iteration":800,"passed_time":1.413848608,"remaining_time":0.3512557714},
{"learn":[2.076471314],"iteration":801,"passed_time":1.415706483,"remaining_time":0.3495135707},
{"learn":[2.075745675],"iteration":802,"passed_time":1.417405968,"remaining_time":0.3477322238},
{"learn":[2.074708797],"iteration":803,"passed_time":1.419098205,"remaining_time":0.3459493137},
{"learn":[2.073716401],"iteration":804,"passed_time":1.421004909,"remaining_time":0.3442185805},
{"learn":[2.071286284],"iteration":805,"passed_time":1.422901799,"remaining_time":0.3424850485},
{"learn":[2.06997886],"iteration":806,"passed_time":1.424741224,"remaining_time":0.3407373683},
{"learn":[2.068859601],"iteration":807,"passed_time":1.426623287,"remaining_time":0.338999593},
{"learn":[2.066822993],"iteration":808,"passed_time":1.428405029,"remaining_time":0.3372377757},
{"learn":[2.065381248],"iteration":809,"passed_time":1.430171661,"remaining_time":0.3354723648},
{"learn":[2.064309911],"iteration":810,"passed_time":1.432145403,"remaining_time":0.3337552173},
{"learn":[2.063340636],"iteration":811,"passed_time":1.433899874,"remaining_time":0.3319866703},
{"learn":[2.062490838],"iteration":812,"passed_time":1.43551829,"remaining_time":0.3301868639},
{"learn":[2.062164444],"iteration":813,"passed_time":1.437236102,"remaining_time":0.3284102149},
{"learn":[2.061468434],"iteration":814,"passed_time":1.438862672,"remaining_time":0.3266129991},
{"learn":[2.058575973],"iteration":815,"passed_time":1.44066389,"remaining_time":0.3248555831},
{"learn":[2.057560549],"iteration":816,"passed_time":1.442472244,"remaining_time":0.323099658},
{"learn":[2.056548852],"iteration":817,"passed_time":1.444120049,"remaining_time":0.3213078837},
{"learn":[2.055585243],"iteration":818,"passed_time":1.445974435,"remaining_time":0.3195621157},
{"learn":[2.053965157],"iteration":819,"passed_time":1.448024646,"remaining_time":0.3178590687},
{"learn":[2.053212542],"iteration":820,"passed_time":1.450027021,"remaining_time":0.3161447464},
{"learn":[2.051640392],"iteration":821,"passed_time":1.451946824,"remaining_time":0.3144118428},
{"learn":[2.049594971],"iteration":822,"passed_time":1.45393583,"remaining_time":0.3126933681},
{"learn":[2.047558542],"iteration":823,"passed_time":1.455658264,"remaining_time":0.3109172992},
{"learn":[2.047401147],"iteration":824,"passed_time":1.457538717,"remaining_time":0.3091748795},
{"learn":[2.046298943],"iteration":825,"passed_time":1.459327305,"remaining_time":0.3074127738},
{"learn":[2.045953522],"iteration":826,"passed_time":1.461085276,"remaining_time":0.3056441993},
{"learn":[2.045864253],"iteration":827,"passed_time":1.462704596,"remaining_time":0.3038468485},
{"learn":[2.045383575],"iteration":828,"passed_time":1.46418517,"remaining_time":0.3020213077},
{"learn":[2.044837924],"iteration":829,"passed_time":1.465696349,"remaining_time":0.3002028667},
{"learn":[2.044425785],"iteration":830,"passed_time":1.467178541,"remaining_time":0.2983792702},
{"learn":[2.043647593],"iteration":831,"passed_time":1.468736281,"remaining_time":0.2965717491},
{"learn":[2.043221013],"iteration":832,"passed_time":1.47025731,"remaining_time":0.2947574678},
{"learn":[2.041085203],"iteration":833,"passed_time":1.472178488,"remaining_time":0.293023536},
{"learn":[2.038537099],"iteration":834,"passed_time":1.473897017,"remaining_time":0.2912491112},
{"learn":[2.037586161],"iteration":835,"passed_time":1.475794277,"remaining_time":0.2895098822},
{"learn":[2.036974341],"iteration":836,"passed_time":1.47742246,"remaining_time":0.2877178745},
{"learn":[2.036777141],"iteration":837,"passed_time":1.479368414,"remaining_time":0.2859876887},
{"learn":[2.034501163],"iteration":838,"passed_time":1.481251704,"remaining_time":0.2842449635},
{"learn":[2.033644594],"iteration":839,"passed_time":1.483221619,"remaining_time":0.2825184036},
{"learn":[2.031505986],"iteration":840,"passed_time":1.485226686,"remaining_time":0.2807979109},
{"learn":[2.029053089],"iteration":841,"passed_time":1.487070862,"remaining_time":0.2790465513},
{"learn":[2.027764021],"iteration":842,"passed_time":1.48886551,"remaining_time":0.2772857473},
{"learn":[2.025033099],"iteration":843,"passed_time":1.490446693,"remaining_time":0.2754854077},
{"learn":[2.023231393],"iteration":844,"passed_time":1.492090515,"remaining_time":0.2736970768},
{"learn":[2.021685165],"iteration":845,"passed_time":1.493911021,"remaining_time":0.2719412497},
{"learn":[2.02157302],"iteration":846,"passed_time":1.495436735,"remaining_time":0.2701320194},
{"learn":[2.021436204],"iteration":847,"passed_time":1.497172291,"remaining_time":0.268361071},
{"learn":[2.020960902],"iteration":848,"passed_time":1.498975659,"remaining_time":0.2666022667},
{"learn":[2.019997739],"iteration":849,"passed_time":1.500816008,"remaining_time":0.2648498838},
{"learn":[2.01939401],"iteration":850,"passed_time":1.502558849,"remaining_time":0.2630802215},
{"learn":[2.017142905],"iteration":851,"passed_time":1.504290476,"remaining_time":0.2613086743},
{"learn":[2.016292574],"iteration":852,"passed_time":1.506066287,"remaining_time":0.259544835},
{"learn":[2.014612902],"iteration":853,"passed_time":1.507902754,"remaining_time":0.2577913374},
{"learn":[2.013494874],"iteration":854,"passed_time":1.509467701,"remaining_time":0.2559915985},
{"learn":[2.011427139],"iteration":855,"passed_time":1.511055,"remaining_time":0.2541961682},
{"learn":[2.009964419],"iteration":856,"passed_time":1.512859286,"remaining_time":0.2524374305},
{"learn":[2.009372531],"iteration":857,"passed_time":1.514592325,"remaining_time":0.250666795},
{"learn":[2.008637613],"iteration":858,"passed_time":1.516215231,"remaining_time":0.2488781694},
{"learn":[2.007628945],"iteration":859,"passed_time":1.518135895,"remaining_time":0.2471384015},
{"learn":[2.005497693],"iteration":860,"passed_time":1.520116056,"remaining_time":0.2454078185},
{"learn":[2.003458294],"iteration":861,"passed_time":1.521769042,"remaining_time":0.2436242782},
{"learn":[2.002512712],"iteration":862,"passed_time":1.523606801,"remaining_time":0.2418703729},
{"learn":[2.00200104],"iteration":863,"passed_time":1.525184328,"remaining_time":0.2400753109},
{"learn":[2.000588597],"iteration":864,"passed_time":1.527463758,"remaining_time":0.2383902975},
{"learn":[1.999462741],"iteration":865,"passed_time":1.529014909,"remaining_time":0.2365912214},
{"learn":[1.997641504],"iteration":866,"passed_time":1.530603055,"remaining_time":0.2347983925},
{"learn":[1.996331383],"iteration":867,"passed_time":1.532256496,"remaining_time":0.2330159649},
{"learn":[1.995545444],"iteration":868,"passed_time":1.533979223,"remaining_time":0.2312442787},
{"learn":[1.993891914],"iteration":869,"passed_time":1.535632315,"remaining_time":0.2294623},
{"learn":[1.993424683],"iteration":870,"passed_time":1.537345749,"remaining_time":0.2276895542},
{"learn":[1.99278047],"iteration":871,"passed_time":1.539190107,"remaining_time":0.2259361625},
{"learn":[1.992471567],"iteration":872,"passed_time":1.541042902,"remaining_time":0.2241837899},
{"learn":[1.991664836],"iteration":873,"passed_time":1.542902265,"remaining_time":0.2224321343},
{"learn":[1.99096976],"iteration":874,"passed_time":1.544558029,"remaining_time":0.220651147},
{"learn":[1.989335728],"iteration":875,"passed_time":1.546168499,"remaining_time":0.2188640341},
{"learn":[1.989024973],"iteration":876,"passed_time":1.547727887,"remaining_time":0.2170701597},
{"learn":[1.988376945],"iteration":877,"passed_time":1.549363747,"remaining_time":0.2152874455},
{"learn":[1.985708824],"iteration":878,"passed_time":1.550789013,"remaining_time":0.2134760757},
{"learn":[1.985123273],"iteration":879,"passed_time":1.552574977,"remaining_time":0.2117147696},
{"learn":[1.984030948],"iteration":880,"passed_time":1.554030452,"remaining_time":0.2099087671},
{"learn":[1.98390797],"iteration":881,"passed_time":1.555782672,"remaining_time":0.20814326},
{"learn":[1.98278255],"iteration":882,"passed_time":1.557475326,"remaining_time":0.2063698903},
{"learn":[1.982135099],"iteration":883,"passed_time":1.558393724,"remaining_time":0.2044951041},
{"learn":[1.980077476],"iteration":884,"passed_time":1.559175186,"remaining_time":0.2026046851},
{"learn":[1.978611428],"iteration":885,"passed_time":1.561115847,"remaining_time":0.2008659217},
{"learn":[1.976991065],"iteration":886,"passed_time":1.56301432,"remaining_time":0.1991213283},
{"learn":[1.976297943],"iteration":887,"passed_time":1.564482034,"remaining_time":0.1973220584},
{"learn":[1.975494076],"iteration":888,"passed_time":1.566174377,"remaining_time":0.1955515814},
{"learn":[1.975453596],"iteration":889,"passed_time":1.567862381,"remaining_time":0.1937807438},
{"learn":[1.974526019],"iteration":890,"passed_time":1.569435141,"remaining_time":0.1919959937},
{"learn":[1.973613157],"iteration":891,"passed_time":1.571275848,"remaining_time":0.1902441609},
{"learn":[1.972802251],"iteration":892,"passed_time":1.572969997,"remaining_time":0.1884745685},
{"learn":[1.972523663],"iteration":893,"passed_time":1.574669959,"remaining_time":0.1867058341},
{"learn":[1.971836668],"iteration":894,"passed_time":1.576817606,"remaining_time":0.184989775},
{"learn":[1.971548982],"iteration":895,"passed_time":1.578720707,"remaining_time":0.1832443678},
{"learn":[1.970993143],"iteration":896,"passed_time":1.580594636,"remaining_time":0.1814952592},
{"learn":[1.970475119],"iteration":897,"passed_time":1.582179464,"remaining_time":0.1797130349},
{"learn":[1.969970936],"iteration":898,"passed_time":1.583680572,"remaining_time":0.177921844},
{"learn":[1.968587623],"iteration":899,"passed_time":1.585567949,"remaining_time":0.1761742165},
{"learn":[1.967985241],"iteration":900,"passed_time":1.587003102,"remaining_time":0.1743765894},
{"learn":[1.966088973],"iteration":901,"passed_time":1.588554613,"remaining_time":0.1725924081},
{"learn":[1.964173478],"iteration":902,"passed_time":1.590205542,"remaining_time":0.1708194215},
{"learn":[1.963893335],"iteration":903,"passed_time":1.591797472,"remaining_time":0.1690404395},
{"learn":[1.96379296],"iteration":904,"passed_time":1.593525707,"remaining_time":0.1672761792},
{"learn":[1.963346654],"iteration":905,"passed_time":1.595085255,"remaining_time":0.1654944966},
{"learn":[1.961962618],"iteration":906,"passed_time":1.596571166,"remaining_time":0.1637057535},
{"learn":[1.961525873],"iteration":907,"passed_time":1.598304311,"remaining_time":0.1619427276},
{"learn":[1.960851479],"iteration":908,"passed_time":1.600131058,"remaining_time":0.1601891378},
{"learn":[1.96005688],"iteration":909,"passed_time":1.601867913,"remaining_time":0.1584264969},
{"learn":[1.959066087],"iteration":910,"passed_time":1.603483813,"remaining_time":0.1566520959},
{"learn":[1.958189279],"iteration":911,"passed_time":1.605098516,"remaining_time":0.154877927},
{"learn":[1.957644806],"iteration":912,"passed_time":1.606313424,"remaining_time":0.1530660109},
{"learn":[1.95623498],"iteration":913,"passed_time":1.608012562,"remaining_time":0.1513009632},
{"learn":[1.954362959],"iteration":914,"passed_time":1.609696057,"remaining_time":0.1495346064},
{"learn":[1.953009324],"iteration":915,"passed_time":1.611376813,"remaining_time":0.1477681794},
{"learn":[1.952404905],"iteration":916,"passed_time":1.61316005,"remaining_time":0.146011215},
{"learn":[1.952189852],"iteration":917,"passed_time":1.61483306,"remaining_time":0.1442443474},
{"learn":[1.95096935],"iteration":918,"passed_time":1.616318562,"remaining_time":0.1424611572},
{"learn":[1.949477881],"iteration":919,"passed_time":1.618000898,"remaining_time":0.1406957303},
{"learn":[1.947289981],"iteration":920,"passed_time":1.619778899,"remaining_time":0.1389386895},
{"learn":[1.947125975],"iteration":921,"passed_time":1.621613623,"remaining_time":0.1371864019},
{"learn":[1.946308944],"iteration":922,"passed_time":1.623350922,"remaining_time":0.1354258082},
{"learn":[1.94485817],"iteration":923,"passed_time":1.625159893,"remaining_time":0.13367116},
{"learn":[1.944467779],"iteration":924,"passed_time":1.627001233,"remaining_time":0.1319190189},
{"learn":[1.943822444],"iteration":925,"passed_time":1.628611204,"remaining_time":0.1301481956},
{"learn":[1.94257504],"iteration":926,"passed_time":1.630257855,"remaining_time":0.1283806078},
{"learn":[1.941609052],"iteration":927,"passed_time":1.632437396,"remaining_time":0.1266546255},
{"learn":[1.941098554],"iteration":928,"passed_time":1.634065031,"remaining_time":0.1248854868},
{"learn":[1.939872195],"iteration":929,"passed_time":1.635986943,"remaining_time":0.1231388022},
{"learn":[1.939719884],"iteration":930,"passed_time":1.637699963,"remaining_time":0.1213762593},
{"learn":[1.939623863],"iteration":931,"passed_time":1.639395143,"remaining_time":0.1196125211},
{"learn":[1.937561218],"iteration":932,"passed_time":1.640905519,"remaining_time":0.1178356589},
{"learn":[1.936079942],"iteration":933,"passed_time":1.642661873,"remaining_time":0.116076749},
{"learn":[1.934490411],"iteration":934,"passed_time":1.644710207,"remaining_time":0.1143381427},
{"learn":[1.933361785],"iteration":935,"passed_time":1.646470403,"remaining_time":0.1125791728},
{"learn":[1.931480153],"iteration":936,"passed_time":1.648435618,"remaining_time":0.110833985},
{"learn":[1.929500365],"iteration":937,"passed_time":1.650286853,"remaining_time":0.1090807941},
{"learn":[1.928616635],"iteration":938,"passed_time":1.651907789,"remaining_time":0.1073124336},
{"learn":[1.92817223],"iteration":939,"passed_time":1.65392456,"remaining_time":0.1055696528},
{"learn":[1.927997652],"iteration":940,"passed_time":1.655475709,"remaining_time":0.1037970955},
{"learn":[1.927516217],"iteration":941,"passed_time":1.657275582,"remaining_time":0.1020403225},
{"learn":[1.926589856],"iteration":942,"passed_time":1.658997817,"remaining_time":0.1002787652},
{"learn":[1.92482098],"iteration":943,"passed_time":1.660656298,"remaining_time":0.09851350922},
{"learn":[1.924256008],"iteration":944,"passed_time":1.662413767,"remaining_time":0.09675424044},
{"learn":[1.923227697],"iteration":945,"passed_time":1.664284379,"remaining_time":0.09500143388},
{"learn":[1.922393934],"iteration":946,"passed_time":1.666362663,"remaining_time":0.0932600012},
{"learn":[1.922308304],"iteration":947,"passed_time":1.667780368,"remaining_time":0.09148162359},
{"learn":[1.920567723],"iteration":948,"passed_time":1.669582647,"remaining_time":0.08972467335},
{"learn":[1.919638142],"iteration":949,"passed_time":1.671353978,"remaining_time":0.08796599887},
{"learn":[1.918426519],"iteration":950,"passed_time":1.673482888,"remaining_time":0.08622572189},
{"learn":[1.917394224],"iteration":951,"passed_time":1.675530409,"remaining_time":0.08448052483},
{"learn":[1.917315628],"iteration":952,"passed_time":1.677360408,"remaining_time":0.08272396558},
{"learn":[1.916653628],"iteration":953,"passed_time":1.679222358,"remaining_time":0.08096879297},
{"learn":[1.915196109],"iteration":954,"passed_time":1.680912554,"remaining_time":0.07920530359},
{"learn":[1.913516204],"iteration":955,"passed_time":1.683169235,"remaining_time":0.07746804009},
{"learn":[1.911812375],"iteration":956,"passed_time":1.684937102,"remaining_time":0.07570772769},
{"learn":[1.910965932],"iteration":957,"passed_time":1.686753765,"remaining_time":0.07394953876},
{"learn":[1.909713215],"iteration":958,"passed_time":1.688542451,"remaining_time":0.07219003181},
{"learn":[1.909201337],"iteration":959,"passed_time":1.690122006,"remaining_time":0.07042175024},
{"learn":[1.907531369],"iteration":960,"passed_time":1.708410756,"remaining_time":0.06933196618},
{"learn":[1.905713265],"iteration":961,"passed_time":1.710854786,"remaining_time":0.06758054246},
{"learn":[1.905075328],"iteration":962,"passed_time":1.713889803,"remaining_time":0.06585038704},
{"learn":[1.903670548],"iteration":963,"passed_time":1.716689922,"remaining_time":0.06410875228},
{"learn":[1.903126115],"iteration":964,"passed_time":1.719404288,"remaining_time":0.06236181357},
{"learn":[1.901158954],"iteration":965,"passed_time":1.72125045,"remaining_time":0.06058231398},
{"learn":[1.900180439],"iteration":966,"passed_time":1.723035044,"remaining_time":0.05880057543},
{"learn":[1.899533482],"iteration":967,"passed_time":1.725301143,"remaining_time":0.05703474854},
{"learn":[1.898789896],"iteration":968,"passed_time":1.727539806,"remaining_time":0.05526701134},
{"learn":[1.89744334],"iteration":969,"passed_time":1.729257163,"remaining_time":0.0534821803},
{"learn":[1.896901658],"iteration":970,"passed_time":1.730913279,"remaining_time":0.0516956592},
{"learn":[1.895803551],"iteration":971,"passed_time":1.73318199,"remaining_time":0.04992705321},
{"learn":[1.89535727],"iteration":972,"passed_time":1.735198388,"remaining_time":0.04815041776},
{"learn":[1.893833017],"iteration":973,"passed_time":1.737336446,"remaining_time":0.04637653758},
{"learn":[1.893463411],"iteration":974,"passed_time":1.73944513,"remaining_time":0.04460115719},
{"learn":[1.892664634],"iteration":975,"passed_time":1.741161597,"remaining_time":0.0428154491},
{"learn":[1.892021332],"iteration":976,"passed_time":1.742916181,"remaining_time":0.04103078011},
{"learn":[1.890955796],"iteration":977,"passed_time":1.745087428,"remaining_time":0.03925554542},
{"learn":[1.890945278],"iteration":978,"passed_time":1.746409873,"remaining_time":0.03746129453},
{"learn":[1.889319109],"iteration":979,"passed_time":1.748381457,"remaining_time":0.03568125422},
{"learn":[1.888868507],"iteration":980,"passed_time":1.749963658,"remaining_time":0.03389328186},
{"learn":[1.888424983],"iteration":981,"passed_time":1.751986113,"remaining_time":0.0321137984},
{"learn":[1.887953752],"iteration":982,"passed_time":1.754475712,"remaining_time":0.03034189939},
{"learn":[1.88705001],"iteration":983,"passed_time":1.755879498,"remaining_time":0.02855088614},
{"learn":[1.884991827],"iteration":984,"passed_time":1.757608278,"remaining_time":0.0267656083},
{"learn":[1.88467518],"iteration":985,"passed_time":1.759530337,"remaining_time":0.02498318937},
{"learn":[1.883776529],"iteration":986,"passed_time":1.761313637,"remaining_time":0.02319865986},
{"learn":[1.883529018],"iteration":987,"passed_time":1.763181593,"remaining_time":0.02141516105},
{"learn":[1.882243373],"iteration":988,"passed_time":1.765249871,"remaining_time":0.01963371949},
{"learn":[1.880651123],"iteration":989,"passed_time":1.767533629,"remaining_time":0.01785387504},
{"learn":[1.879960531],"iteration":990,"passed_time":1.769520584,"remaining_time":0.01607031812},
{"learn":[1.879542362],"iteration":991,"passed_time":1.77094594,"remaining_time":0.0142818221},
{"learn":[1.877869202],"iteration":992,"passed_time":1.772767326,"remaining_time":0.01249684923},
{"learn":[1.877523368],"iteration":993,"passed_time":1.774792683,"remaining_time":0.01071303431},
{"learn":[1.877030237],"iteration":994,"passed_time":1.776895621,"remaining_time":0.008929123726},
{"learn":[1.876786537],"iteration":995,"passed_time":1.778915648,"remaining_time":0.007144239551},
{"learn":[1.874869337],"iteration":996,"passed_time":1.781010634,"remaining_time":0.005359109231},
{"learn":[1.873212413],"iteration":997,"passed_time":1.782843582,"remaining_time":0.003572832829},
{"learn":[1.87233344],"iteration":998,"passed_time":1.784888996,"remaining_time":0.001786675672},
{"learn":[1.871119229],"iteration":999,"passed_time":1.787190862,"remaining_time":0}
]}